Workbook

Sheet 120180 MVA Transformer
B2: Supplier Feedback - 120/180 MVA Transformer
B3: Dealer | C3: Manufacturer | D3: Lead Time (wks) | E3: Estimated Cost | F3: Estimated Delivery | G3: Production Slot Purchasing? | H3: Additional Notes
B4: Power Asset Recovery Corp. | F4: =IF(D4="","",TODAY()+D4*7+30) | H4: Searching
B5: Mars Transformers | D5: 76 | F5: =IF(D5="","",TODAY()+D5*7+30) -> 46638 | H5: Recommended 13.8kv on Secondary Side
B6: Virginia Transformer | D6: 56 | F6: =IF(D6="","",TODAY()+D6*7+30) -> 46498
B7: Sunbelt | F7: =IF(D7="","",TODAY()+D7*7+30) | H7: No Quote - Can't Find Anything
F8: =IF(D8="","",TODAY()+D8*7+30)
F9: =IF(D9="","",TODAY()+D9*7+30)
F10: =IF(D10="","",TODAY()+D10*7+30)
F11: =IF(D11="","",TODAY()+D11*7+30)
F12: =IF(D12="","",TODAY()+D12*7+30)
F13: =IF(D13="","",TODAY()+D13*7+30)
F14: =IF(D14="","",TODAY()+D14*7+30)
F15: =IF(D15="","",TODAY()+D15*7+30)
B17: Option 1
B18: 120/160/200//224 MVA 138kv Delta - 34.5kv Grounded Wye Secondary
B19: Option 2
B20: 180/240/300//336 MVA 138kv Delta - 34.5kv Grounded Wye Secondary

Sheet PV Fiberlight
B1: Option 1 | C1: Option 2 | D1: Option 3 | E1: Option 4 | G1: Rate (annual)
A2: Upfront | B2: 250000 | C2: 125000 | D2: 65000 | E2: 0 | G2: 0.1
A3: 60 Months (Monthly Payment) | B3: 3750 | C3: 9250 | D3: 12650 | E3: =15500 -> 15500 | G3: Rate (monthly)
A4: Total | B4: =B2+(B3*60) -> 475000 | C4: =C2+(C3*60) -> 680000 | D4: =D2+(D3*60) -> 824000 | E4: =E2+(E3*60) -> 930000 | G4: =(1+G2)^(1/12)-1 -> 0.0079741404
A7: PV of Monthly | B7: =B3*(1-(1/(1+$G$4)^60))/$G$4 -> 178269.38 | C7: =C3*(1-(1/(1+$G$4)^60))/$G$4 -> 439731.13 | D7: =D3*(1-(1/(1+$G$4)^60))/$G$4 -> 601362.03 | E7: =E3*(1-(1/(1+$G$4)^60))/$G$4 -> 736846.75
A8: Total PV | B8: =B7+B2 -> 428269.38 | C8: =C7+C2 -> 564731.13 | D8: =D7+D2 -> 666362.03 | E8: =E7+E2 -> 736846.75

Sheet Summary
B1: Container | C1: Miner Type | D1: Status | E1: Miner Capacity | F1: Miner Manufacturer | G1: Phase | H1: Feeder Name | I1: Switch # | J1: High Voltage | K1: XF # | L1: XF SN | M1: XF Manufacturer | N1: XF KvA | O1: Fluid Type | P1: Container Manufacturer | Q1: Notes
B2: *TP01 | C2: Mara T2 | D2: Deployed | E2: 160 | F2: Bitmain | G2: 0 | H2: 1A | I2: SW001-A | J2: 6.9KV | K2: XF000 | L2: 2301102024 | M2: CIE | N2: 2550 | O2: OIL | P2: Fbox
B3: *TP02 | C3: Whatsminer M63S | D3: Energized | E3: --- | F3: MicroBT | G3: 0 | H3: 1A | I3: SW001-A | J3: 6.9KV | K3: ***** | L3: ********** | M3: ********** | N3: ***** | P3: Hydro | Q3: Hash House
B4: C000 | C4: Mara T2 | D4: Deployed | E4: 160 | F4: Bitmain | G4: 0 | H4: 1A | I4: SW001-A | J4: 6.9KV | K4: XF001 | L4: N/A | M4: N/A | N4: N/A | O4: N/A | P4: Fbox
B5: C001 | C5: Teraflux AI3680 | D5: Deployed | E5: 128 | F5: Auradine | G5: 0 | H5: 1A | I5: SW001-A | J5: 6.9KV | K5: ***** | L5: ********** | M5: ********** | N5: ***** | P5: Submer
B6: C002 | C6: Teraflux AI3680 | D6: Deployed | E6: 128 | F6: Auradine | G6: 0 | H6: 1A | I6: SW001-A | J6: 6.9KV | K6: XF002 | L6: ST1121-353957 | M6: Sunbelt | N6: 2000 | O6: OIL | P6: Submer
B7: C003 | C7: BixBit Hydro | D7: Offline | E7: 0 | G7: 0 | H7: 1A | I7: SW001-A | J7: 6.9KV | K7: ***** | L7: ********** | M7: ********** | N7: ***** | P7: Hydro
B8: C004 | C8: Whatsminer M56S++ | D8: Deployed | E8: 128 | F8: MicroBT | G8: 1 | H8: 11A | I8: SW002-A | J8: 34.5KV | K8: XF003 | L8: 2406041 | M8: Jiangsu Dabbojin | N8: 2600 | O8: FR3 | P8: Fbox
B9: C005 | C9: Whatsminer M56S++ | D9: Deployed | E9: 128 | F9: MicroBT | G9: 1 | H9: 11A | I9: SW002-A | J9: 34.5KV | K9: ***** | L9: ********** | M9: ********** | N9: ***** | P9: Fbox
B10: C006 | C10: Whatsminer M56S++ | D10: Deployed | E10: 128 | F10: MicroBT | G10: 1 | H10: 11A | I10: SW002-B | J10: 34.5KV | K10: XF004 | L10: 2406040 | M10: Jiangsu Dabbojin | N10: 2600 | O10: FR3 | P10: Fbox
B11: C007 | C11: Whatsminer M56S++ | D11: Deployed | E11: 128 | F11: MicroBT | G11: 1 | H11: 11A | I11: SW002-B | J11: 34.5KV | K11: ***** | L11: ********** | M11: ********** | N11: ***** | P11: Fbox
B12: C008 | C12: Whatsminer M56S++ | D12: Deployed | E12: 128 | F12: MicroBT | G12: 1 | H12: 11A | I12: SW002-B | J12: 34.5KV | K12: XF005 | L12: 2406072 | M12: Jiangsu Dabbojin | N12: 2600 | O12: FR3 | P12: Fbox
B13: C009 | C13: Whatsminer M56S++ | D13: Deployed | E13: 128 | F13: MicroBT | G13: 1 | H13: 11A | I13: SW002-B | J13: 34.5KV | K13: ***** | L13: ********** | M13: ********** | N13: ***** | P13: Fbox
B14: C010 | C14: Whatsminer M56S++ | D14: Deployed | E14: 128 | F14: MicroBT | G14: 1+ | H14: 11B | I14: SW003-A | J14: 34.5KV | K14: XF006 | L14: JC 2800-2415 | M14: JCL Energy | N14: 2600 | O14: OIL | P14: Fbox
B15: C011 | C15: Whatsminer M56S++ | D15: Deployed | E15: 128 | F15: MicroBT | G15: 1+ | H15: 11B | I15: SW003-A | J15: 34.5KV | K15: ***** | L15: ********** | M15: ********** | N15: ***** | P15: Fbox
B16: C012 | C16: Whatsminer M56S++ | D16: Deployed | E16: 128 | F16: MicroBT | G16: 1+ | H16: 11B | I16: SW003-A | J16: 34.5KV | K16: XF007 | L16: JC2600-2418 | M16: JCL Energy | N16: 2600 | O16: OIL | P16: Fbox
B17: C013 | C17: Whatsminer M66S | D17: Deployed | E17: 128 | F17: MicroBT | G17: 1+ | H17: 11B | I17: SW003-A | J17: 34.5KV | K17: ***** | L17: ********** | M17: ********** | N17: ***** | P17: Fbox
B18: C014 | C18: Greenhash Hydro | D18: Energized | E18: 0 | G18: 0 | H18: 1B | I18: SW001-B | J18: 6.9KV | K18: XF008 | L18: ST1121-353953 | M18: Sunbelt | N18: 2000 | O18: FR3 | P18: Hydro
B19: C015 | C19: Fog Hashing Hydro | D19: Energized | E19: 0 | G19: 0 | H19: 1B | I19: SW001-B | J19: 6.9KV | K19: ***** | L19: ********** | M19: ********** | N19: ***** | P19: Hydro
B20: C016 | C20: Fbox Hydro | D20: Deployed | E20: 0 | G20: 0 | H20: 2A | I20: SW001-C | J20: 6.9KV | K20: XF009 | L20: ST1121-353951 | M20: Sunbelt | N20: 2000 | O20: FR3 | P20: Hydro
B21: C017 | C21: Antminer S21 | D21: Deployed | E21: 160 | F21: Bitmain | G21: 0 | H21: 2A | I21: SW001-C | J21: 6.9KV | K21: ***** | L21: ********** | M21: ********** | N21: ***** | P21: Fbox
B22: C018 | C22: Whatsminer M56S++ | D22: Deployed | E22: 128 | F22: MicroBT | G22: 1 | H22: 11A | I22: SW002-A | J22: 34.5KV | K22: XF010 | L22: 2406081 | M22: Jiangsu Dabbojin | N22: 2600 | O22: FR3 | P22: Fbox
B23: C019 | C23: Whatsminer M56S++ | D23: Deployed | E23: 128 | F23: MicroBT | G23: 1 | H23: 11A | I23: SW002-A | J23: 34.5KV | K23: ***** | L23: ********** | M23: ********** | N23: ***** | P23: Fbox
B24: C020 | C24: Whatsminer M56S++ | D24: Deployed | E24: 128 | F24: MicroBT | G24: 1 | H24: 11A | I24: SW002-B | J24: 34.5KV | K24: XF011 | L24: 2406094 | M24: Jiangsu Dabbojin | N24: 2600 | O24: FR3 | P24: Fbox
B25: C021 | C25: Whatsminer M56S++ | D25: Deployed | E25: 128 | F25: MicroBT | G25: 1 | H25: 11A | I25: SW002-B | J25: 34.5KV | K25: ***** | L25: ********** | M25: ********** | N25: ***** | P25: Fbox
B26: C022 | C26: Whatsminer M56S++ | D26: Deployed | E26: 128 | F26: MicroBT | G26: 1 | H26: 11A | I26: SW002-B | J26: 34.5KV | K26: XF012 | L26: 2406093 | M26: Jiangsu Dabbojin | N26: 2600 | O26: FR3 | P26: Fbox
B27: C023 | C27: Whatsminer M56S++ | D27: Deployed | E27: 128 | F27: MicroBT | G27: 1 | H27: 11A | I27: SW002-B | J27: 34.5KV | K27: ***** | L27: ********** | M27: ********** | N27: ***** | P27: Fbox
B28: C024 | C28: Whatsminer M56S++ | D28: Deployed | E28: 128 | F28: MicroBT | G28: 1+ | H28: 11B | I28: SW003-A | J28: 34.5KV | K28: XF013 | L28: JC2600-2413 | M28: JCL Energy | N28: 2600 | O28: OIL | P28: Fbox
B29: C025 | C29: Whatsminer M56S++ | D29: Deployed | E29: 128 | F29: MicroBT | G29: 1+ | H29: 11B | I29: SW003-A | J29: 34.5KV | K29: ***** | L29: ********** | M29: ********** | N29: ***** | P29: Fbox
B30: C026 | C30: Whatsminer M56S++ | D30: Deployed | E30: 128 | F30: MicroBT | G30: 1+ | H30: 11B | I30: SW003-A | J30: 34.5KV | K30: XF014 | L30: JC2600-2416 | M30: JCL Energy | N30: 2600 | O30: OIL | P30: Fbox
B31: C027 | C31: Whatsminer M56S++ | D31: Deployed | E31: 128 | F31: MicroBT | G31: 1+ | H31: 11B | I31: SW003-A | J31: 34.5KV | K31: ***** | L31: ********** | M31: ********** | N31: ***** | P31: Fbox
B32: C028 | C32: Antminer S21 | D32: Deployed | E32: 160 | F32: Bitmain | G32: 0 | H32: 1B | I32: SW001-B | J32: 6.9KV | K32: XF015 | L32: ST1121-353960 | M32: Sunbelt | N32: 2000 | O32: FR3 | P32: Fbox
B33: C029 | C33: Antminer S21 | D33: Deployed | E33: 160 | F33: Bitmain | G33: 0 | H33: 1B | I33: SW001-B | J33: 6.9KV | K33: ***** | L33: ********** | M33: ********** | N33: ***** | P33: Fbox
B34: C030 | C34: Antminer S21 | D34: Deployed | E34: 160 | F34: Bitmain | G34: 0 | H34: 2A | I34: SW001-C | J34: 6.9KV | K34: XF016 | L34: ST1121-353962 | M34: Sunbelt | N34: 2000 | O34: FR3 | P34: Fbox
B35: C031 | C35: Antminer S21 | D35: Deployed | E35: 160 | F35: Bitmain | G35: 0 | H35: 2A | I35: SW001-C | J35: 6.9KV | K35: ***** | L35: ********** | M35: ********** | N35: ***** | P35: Fbox
B36: C032 | C36: Whatsminer M56S++ | D36: Deployed | E36: 128 | F36: MicroBT | G36: 1 | H36: 11A | I36: SW002-A | J36: 34.5KV | K36: XF017 | L36: 2406097 | M36: Jiangsu Dabbojin | N36: 2600 | O36: FR3 | P36: Fbox
B37: C033 | C37: Whatsminer M56S++ | D37: Deployed | E37: 128 | F37: MicroBT | G37: 1 | H37: 11A | I37: SW002-A | J37: 34.5KV | K37: ***** | L37: ********** | M37: ********** | N37: ***** | P37: Fbox
B38: C034 | C38: Whatsminer M56S++ | D38: Deployed | E38: 128 | F38: MicroBT | G38: 1 | H38: 11A | I38: SW002-B | J38: 34.5KV | K38: XF018 | L38: 2406080 | M38: Jiangsu Dabbojin | N38: 2600 | O38: FR3 | P38: Fbox
B39: C035 | C39: Whatsminer M56S++ | D39: Deployed | E39: 128 | F39: MicroBT | G39: 1 | H39: 11A | I39: SW002-B | J39: 34.5KV | K39: ***** | L39: ********** | M39: ********** | N39: ***** | P39: Fbox
B40: C036 | C40: Whatsminer M56S++ | D40: Deployed | E40: 128 | F40: MicroBT | G40: 1 | H40: 11A | I40: SW002-B | J40: 34.5KV | K40: XF019 | L40: 2406046 | M40: Jiangsu Dabbojin | N40: 2600 | O40: FR3 | P40: Fbox
B41: C037 | C41: Whatsminer M56S++ | D41: Deployed | E41: 128 | F41: MicroBT | G41: 1 | H41: 11A | I41: SW002-B | J41: 34.5KV | K41: ***** | L41: ********** | M41: ********** | N41: ***** | P41: Fbox
B42: C038 | C42: Whatsminer M56S++ | D42: Deployed | E42: 128 | F42: MicroBT | G42: 1+ | H42: 11B | I42: SW003-A | J42: 34.5KV | K42: XF020 | L42: JC2600-2414 | M42: JCL Energy | N42: 2600 | O42: OIL | P42: Fbox
B43: C039 | C43: Whatsminer M56S++ | D43: Deployed | E43: 128 | F43: MicroBT | G43: 1+ | H43: 11B | I43: SW003-A | J43: 34.5KV | K43: ***** | L43: ********** | M43: ********** | N43: ***** | P43: Fbox
B44: C040 | C44: Antminer S21 | D44: Deployed | E44: 160 | F44: Bitmain | G44: 1+ | H44: 11B | I44: SW003-A | J44: 34.5KV | K44: XF021 | L44: 2406037 | M44: Jiangsu Dabbojin | N44: 2600 | O44: FR3 | P44: Fbox
B45: C041 | C45: Antminer S21 | D45: Deployed | E45: 160 | F45: Bitmain | G45: 1+ | H45: 11B | I45: SW003-A | J45: 34.5KV | K45: ***** | L45: ********** | M45: ********** | N45: ***** | P45: Fbox
B46: C042 | C46: Antminer S21 | D46: Deployed | E46: 160 | F46: Bitmain | G46: 0 | H46: 1B | I46: SW001-B | J46: 6.9KV | K46: XF022 | L46: ST1121-353955 | M46: Sunbelt | N46: 2000 | O46: OIL | P46: Fbox
B47: C043 | C47: Antminer S21 | D47: Deployed | E47: 160 | F47: Bitmain | G47: 0 | H47: 1B | I47: SW001-B | J47: 6.9KV | K47: ***** | L47: ********** | M47: ********** | N47: ***** | P47: Fbox
B48: C044 | C48: Antminer S21 | D48: Deployed | E48: 160 | F48: Bitmain | G48: 0 | H48: 2A | I48: SW001-C | J48: 6.9KV | K48: XF023 | L48: TBV8381-01 | M48: Sunbelt | N48: 2000 | O48: FR3 | P48: Fbox
B49: C045 | C49: Antminer S21 | D49: Deployed | E49: 160 | F49: Bitmain | G49: 0 | H49: 2A | I49: SW001-C | J49: 6.9KV | K49: ***** | L49: ********** | M49: ********** | N49: ***** | P49: Fbox
B50: C046 | C50: Antminer S21 | D50: Deployed | E50: 160 | F50: Bitmain | G50: 1 | H50: 11A | I50: SW002-A | J50: 34.5KV | K50: XF024 | L50: 2406038 | M50: Jiangsu Dabbojin | N50: 2600 | O50: FR3 | P50: Fbox
B51: C047 | C51: Antminer S21 | D51: Deployed | E51: 160 | F51: Bitmain | G51: 1 | H51: 11A | I51: SW002-A | J51: 34.5KV | K51: ***** | L51: ********** | M51: ********** | N51: ***** | P51: Fbox
B52: C048 | C52: TAE BESS | D52: Offline | F52: -- | G52: 1 | H52: 11A | I52: SW002-B | J52: 34.5KV | K52: XF025 | L52: 2406082 | M52: Jiangsu Dabbojin | N52: 2600 | O52: FR3 | P52: TAE | Q52: Not Installed
B53: C049 | C53: Whatsminer M56S++ | D53: Deployed | E53: 128 | F53: MicroBT | G53: 1 | H53: 11A | I53: SW002-B | J53: 34.5KV | K53: ***** | L53: ********** | M53: ********** | N53: ***** | P53: Fbox
B54: C050 | C54: Whatsminer M56S++ | D54: Deployed | E54: 128 | F54: MicroBT | G54: 1 | H54: 11A | I54: SW002-B | J54: 34.5KV | K54: XF026 | L54: 2406098 | M54: Jiangsu Dabbojin | N54: 2600 | O54: FR3 | P54: Fbox
B55: C051 | C55: Whatsminer M56S++ | D55: Deployed | E55: 128 | F55: MicroBT | G55: 1 | H55: 11A | I55: SW002-B | J55: 34.5KV | K55: ***** | L55: ********** | M55: ********** | N55: ***** | P55: Fbox
B56: C052 | C56: Whatsminer M56S++ / M66S | D56: Deployed | E56: 128 | F56: MicroBT | G56: 1+ | H56: 11B | I56: SW003-A | J56: 34.5KV | K56: XF027 | L56: JC2600-2408 | M56: JCL Energy | N56: 2600 | O56: OIL | P56: Fbox
B57: C053 | C57: Whatsminer M66S | D57: Deployed | E57: 128 | F57: MicroBT | G57: 1+ | H57: 11B | I57: SW003-A | J57: 34.5KV | K57: ***** | L57: ********** | M57: ********** | N57: ***** | P57: Fbox
B58: C054 | C58: Antminer S21 | D58: Deployed | E58: 160 | F58: Bitmain | G58: 1+ | H58: 11B | I58: SW003-A | J58: 34.5KV | K58: XF028 | L58: 2406089 | M58: Jiangsu Dabbojin | N58: 2600 | O58: FR3 | P58: Fbox
B59: C055 | C59: Antminer S21 | D59: Deployed | E59: 160 | F59: Bitmain | G59: 1+ | H59: 11B | I59: SW003-A | J59: 34.5KV | K59: ***** | L59: ********** | M59: ********** | N59: ***** | P59: Fbox
B60: C056 | C60: Antminer S21 | D60: Deployed | E60: 160 | F60: Bitmain | G60: 1+ | H60: 11B | I60: SW003-B | J60: 34.5KV | K60: XF029 | L60: 2406083 | M60: Jiangsu Dabbojin | N60: 2600 | O60: FR3 | P60: Fbox
B61: C057 | C61: Antminer S21 | D61: Deployed | E61: 160 | F61: Bitmain | G61: 1+ | H61: 11B | I61: SW003-B | J61: 34.5KV | K61: ***** | L61: ********** | M61: ********** | N61: ***** | P61: Fbox
B62: C058 | C62: Antminer S21 | D62: Deployed | E62: 160 | F62: Bitmain | G62: 1+ | H62: 11B | I62: SW003-B | J62: 34.5KV | K62: XF030 | L62: 2406051 | M62: Jiangsu Dabbojin | N62: 2600 | O62: FR3 | P62: Fbox
B63: C059 | C63: Antminer S21 | D63: Deployed | E63: 160 | F63: Bitmain | G63: 1+ | H63: 11B | I63: SW003-B | J63: 34.5KV | K63: ***** | L63: ********** | M63: ********** | N63: ***** | P63: Fbox
B64: C060 | C64: Antminer S21 | D64: Deployed | E64: 160 | F64: Bitmain | G64: 1+ | H64: 11B | I64: SW003-B | J64: 34.5KV | K64: XF031 | L64: 2406053 | M64: Jiangsu Dabbojin | N64: 2600 | O64: FR3 | P64: Fbox
B65: C061 | C65: Antminer S21 | D65: Deployed | E65: 160 | F65: Bitmain | G65: 1+ | H65: 11B | I65: SW003-B | J65: 34.5KV | K65: ***** | L65: ********** | M65: ********** | N65: ***** | P65: Fbox
B66: C062 | C66: Antminer S21 | D66: Deployed | E66: 160 | F66: Bitmain | G66: 1+ | H66: 11B | I66: SW003-B | J66: 34.5KV | K66: XF032 | L66: 2406099 | M66: Jiangsu Dabbojin | N66: 2600 | O66: FR3 | P66: Fbox
B67: C063 | C67: Antminer S21 | D67: Deployed | E67: 160 | F67: Bitmain | G67: 1+ | H67: 11B | I67: SW003-B | J67: 34.5KV | K67: ***** | L67: ********** | M67: ********** | N67: ***** | P67: Fbox
B68: C064 | C68: Antminer S21 | D68: Deployed | E68: 160 | F68: Bitmain | G68: 1+ | H68: 11B | I68: SW003-B | J68: 34.5KV | K68: XF033 | L68: 2406071 | M68: Jiangsu Dabbojin | N68: 2600 | O68: FR3 | P68: Fbox
B69: C065 | C69: Antminer S21 | D69: Deployed | E69: 160 | F69: Bitmain | G69: 1+ | H69: 11B | I69: SW003-B | J69: 34.5KV | K69: ***** | L69: ********** | M69: ********** | N69: ***** | P69: Fbox
B70: C066 | C70: Antminer S21 | D70: Deployed | E70: 160 | F70: Bitmain | G70: 1+ | H70: 11B | I70: SW003-B | J70: 34.5KV | K70: XF034 | L70: 2406054 | M70: Jiangsu Dabbojin | N70: 2600 | O70: FR3 | P70: Fbox
B71: C067 | C71: Antminer S21 | D71: Deployed | E71: 160 | F71: Bitmain | G71: 1+ | H71: 11B | I71: SW003-B | J71: 34.5KV | K71: ***** | L71: ********** | M71: ********** | N71: ***** | P71: Fbox
B72: C068 | C72: Antminer S21 | D72: Deployed | E72: 160 | F72: Bitmain | G72: 1+ | H72: 11B | I72: SW003-B | J72: 34.5KV | K72: XF035 | L72: 20112290433 | M72: Sunbelt | N72: 2000 | O72: OIL | P72: Fbox
B73: C069 | C73: Antminer S21 | D73: Deployed | E73: 160 | F73: Bitmain | G73: 1+ | H73: 11B | I73: SW003-B | J73: 34.5KV | K73: ***** | L73: ********** | M73: ********** | N73: ***** | P73: Fbox
B74: C070 | C74: Antminer S21 | D74: Deployed | E74: 160 | F74: Bitmain | G74: 1+ | H74: 11B | I74: SW003-B | J74: 34.5KV | K74: XF036 | L74: 20112290338 | M74: Sunbelt | N74: 2000 | O74: OIL | P74: Fbox
B75: C071 | C75: Antminer S21 | D75: Deployed | E75: 160 | F75: Bitmain | G75: 1+ | H75: 11B | I75: SW003-B | J75: 34.5KV | K75: ***** | L75: ********** | M75: ********** | N75: ***** | P75: Fbox
B76: C072 | C76: Antminer S21 | D76: Deployed | E76: 160 | F76: Bitmain | G76: 2 | H76: 11C | I76: SW004-A | J76: 34.5KV | K76: XF037 | L76: M22E15968 | M76: Sunbelt | N76: 2000 | O76: OIL | P76: Fbox
B77: C073 | C77: Antminer S21 | D77: Deployed | E77: 160 | F77: Bitmain | G77: 2 | H77: 11C | I77: SW004-A | J77: 34.5KV | K77: ***** | L77: ********** | M77: ********** | N77: ***** | P77: Fbox
B78: C074 | C78: Antminer S21 | D78: Deployed | E78: 160 | F78: Bitmain | G78: 2 | H78: 11C | I78: SW004-A | J78: 34.5KV | K78: XF038 | L78: M22D24605 | M78: Sunbelt | N78: 2000 | O78: OIL | P78: Fbox
B79: C075 | C79: Antminer S21 | D79: Deployed | E79: 160 | F79: Bitmain | G79: 2 | H79: 11C | I79: SW004-A | J79: 34.5KV | K79: ***** | L79: ********** | M79: ********** | N79: ***** | P79: Fbox
B80: C076 | C80: Antminer S21 | D80: Deployed | E80: 160 | F80: Bitmain | G80: 2 | H80: 11C | I80: SW004-A | J80: 34.5KV | K80: XF039 | L80: M22E15969 | M80: Sunbelt | N80: 2000 | O80: OIL | P80: Fbox
B81: C077 | C81: Antminer S21 | D81: Deployed | E81: 160 | F81: Bitmain | G81: 2 | H81: 11C | I81: SW004-A | J81: 34.5KV | K81: ***** | L81: ********** | M81: ********** | N81: ***** | P81: Fbox
B82: C078 | C82: Antminer S21 | D82: Deployed | E82: 160 | F82: Bitmain | G82: 2 | H82: 11C | I82: SW004-A | J82: 34.5KV | K82: XF040 | L82: 20112290346 | M82: Sunbelt | N82: 2000 | O82: OIL | P82: Fbox
B83: C079 | C83: Antminer S21 | D83: Deployed | E83: 160 | F83: Bitmain | G83: 2 | H83: 11C | I83: SW004-A | J83: 34.5KV | K83: ***** | L83: ********** | M83: ********** | N83: ***** | P83: Fbox
B84: C080 | C84: Antminer S21 | D84: Deployed | E84: 160 | F84: Bitmain | G84: 2 | H84: 11C | I84: SW004-B | J84: 34.5KV | K84: XF041 | L84: M222D24612 | M84: Sunbelt | N84: 2000 | O84: OIL | P84: Fbox
B85: C081 | C85: Antminer S21 | D85: Deployed | E85: 160 | F85: Bitmain | G85: 2 | H85: 11C | I85: SW004-B | J85: 34.5KV | K85: ***** | L85: ********** | M85: ********** | N85: ***** | P85: Fbox
B86: C082 | C86: Antminer S21 | D86: Deployed | E86: 160 | F86: Bitmain | G86: 2 | H86: 11C | I86: SW004-B | J86: 34.5KV | K86: XF042 | L86: M21F19311 | M86: Sunbelt | N86: 2000 | O86: OIL | P86: Fbox
B87: C083 | C87: Antminer S21 | D87: Deployed | E87: 160 | F87: Bitmain | G87: 2 | H87: 11C | I87: SW004-B | J87: 34.5KV | K87: ***** | L87: ********** | M87: ********** | N87: ***** | P87: Fbox
B88: C084 | C88: Antminer S21 | D88: Deployed | E88: 160 | F88: Bitmain | G88: 2 | H88: 11C | I88: SW004-B | J88: 34.5KV | K88: XF043 | L88: 20112290444 | M88: Sunbelt | N88: 2000 | O88: OIL | P88: Fbox
B89: C085 | C89: Antminer S21 | D89: Deployed | E89: 160 | F89: Bitmain | G89: 2 | H89: 11C | I89: SW004-B | J89: 34.5KV | K89: ***** | L89: ********** | M89: ********** | N89: ***** | P89: Fbox
B90: C086 | C90: Antminer S21 | D90: Deployed | E90: 160 | F90: Bitmain | G90: 2 | H90: 11C | I90: SW004-B | J90: 34.5KV | K90: XF044 | L90: 20112290416 | M90: Sunbelt | N90: 2000 | O90: OIL | P90: Fbox
B91: C087 | C91: Antminer S21 | D91: Deployed | E91: 160 | F91: Bitmain | G91: 2 | H91: 11C | I91: SW004-B | J91: 34.5KV | K91: ***** | L91: ********** | M91: ********** | N91: ***** | P91: Fbox
B92: C088 | C92: Antminer S21 | D92: Deployed | E92: 160 | F92: Bitmain | G92: 3 | H92: 12A | I92: SW005-A | J92: 34.5KV | K92: XF045 | L92: M22D24604 | M92: Sunbelt | N92: 2000 | O92: OIL | P92: Fbox
B93: C089 | C93: Antminer S21 | D93: Deployed | E93: 160 | F93: Bitmain | G93: 3 | H93: 12A | I93: SW005-A | J93: 34.5KV | K93: ***** | L93: ********** | M93: ********** | N93: ***** | P93: Fbox
B94: C090 | C94: Antminer S21 | D94: Deployed | E94: 160 | F94: Bitmain | G94: 3 | H94: 12A | I94: SW005-A | J94: 34.5KV | K94: XF046 | L94: M22D24603 | M94: Sunbelt | N94: 2000 | O94: OIL | P94: Fbox
B95: C091 | C95: Antminer S21 | D95: Deployed | E95: 160 | F95: Bitmain | G95: 3 | H95: 12A | I95: SW005-A | J95: 34.5KV | K95: ***** | L95: ********** | M95: ********** | N95: ***** | P95: Fbox
B96: C092 | C96: Antminer S21 | D96: Deployed | E96: 160 | F96: Bitmain | G96: 3 | H96: 12A | I96: SW005-A | J96: 34.5KV | K96: XF047 | L96: M21F19627 | M96: Sunbelt | N96: 2000 | O96: OIL | P96: Fbox
B97: C093 | C97: Antminer S21 | D97: Deployed | E97: 160 | F97: Bitmain | G97: 3 | H97: 12A | I97: SW005-A | J97: 34.5KV | K97: ***** | L97: ********** | M97: ********** | N97: ***** | P97: Fbox
B98: C094 | C98: Antminer S21 | D98: Deployed | E98: 160 | F98: Bitmain | G98: 3 | H98: 12A | I98: SW005-A | J98: 34.5KV | K98: XF048 | L98: M22D24607 | M98: Sunbelt | N98: 2000 | O98: OIL | P98: Fbox
B99: C095 | C99: Antminer S21 | D99: Deployed | E99: 160 | F99: Bitmain | G99: 3 | H99: 12A | I99: SW005-A | J99: 34.5KV | K99: ***** | L99: ********** | M99: ********** | N99: ***** | P99: Fbox
B100: C096 | C100: Antminer S21 | D100: Deployed | E100: 160 | F100: Bitmain | G100: 3 | H100: 12A | I100: SW005-A | J100: 34.5KV | K100: XF049 | L100: 20112290347 | M100: Sunbelt | N100: 2000 | O100: OIL | P100: Fbox
...

Sheet IP Ranges - Air
A1: Miner Type | B1: Container | C1: Group A | D1: Group B | E1: Group C | F1: Group D
A2: =_xlfn.XLOOKUP(B2,Summary!B:B,Summary!C:C,"") -> Whatsminer M60S | B2: C188 | C2: 10.31.0 | D2: 10.31.1 | E2: 10.31.2 | F2: 10.31.3 | I2: =H2&".0-255" -> .0-255
A3: =_xlfn.XLOOKUP(B3,Summary!B:B,Summary!C:C,"") -> Whatsminer M60S | B3: C209 | C3: 10.31.4 | D3: 10.31.5 | E3: 10.31.6 | F3: 10.31.7 | I3: =H3&".0-255" -> .0-255
A4: =_xlfn.XLOOKUP(B4,Summary!B:B,Summary!C:C,"") -> Empty | B4: C210 | C4: 10.31.8 | D4: 10.31.9 | E4: 10.31.10 | F4: 10.31.11 | I4: =H4&".0-255" -> .0-255
A5: =_xlfn.XLOOKUP(B5,Summary!B:B,Summary!C:C,"") -> Whatsminer M60S | B5: C223 | C5: 10.31.12 | D5: 10.31.13 | E5: 10.31.14 | F5: 10.31.15 | I5: =H5&".0-255" -> .0-255
A6: =_xlfn.XLOOKUP(B6,Summary!B:B,Summary!C:C,"") -> Whatsminer M60S | B6: C224 | C6: 10.31.16 | D6: 10.31.17 | E6: 10.31.18 | F6: 10.31.19 | I6: =H6&".0-255" -> .0-255
A7: =_xlfn.XLOOKUP(B7,Summary!B:B,Summary!C:C,"") -> Empty | B7: C225 | C7: 10.31.20 | D7: 10.31.21 | E7: 10.31.22 | F7: 10.31.23 | I7: =H7&".0-255" -> .0-255
A8: =_xlfn.XLOOKUP(B8,Summary!B:B,Summary!C:C,"") -> Whatsminer M60S | B8: C226 | C8: 10.31.24 | D8: 10.31.25 | E8: 10.31.26 | F8: 10.31.27 | I8: =H8&".0-255" -> .0-255
A9: =_xlfn.XLOOKUP(B9,Summary!B:B,Summary!C:C,"") -> Whatsminer M60 | B9: C239 | C9: 10.31.28 | D9: 10.31.29 | E9: 10.31.30 | F9: 10.31.31 | I9: =H9&".0-255" -> .0-255
A10: =_xlfn.XLOOKUP(B10,Summary!B:B,Summary!C:C,"") -> Empty | B10: C240 | C10: 10.31.32 | D10: 10.31.33 | E10: 10.31.34 | F10: 10.31.35 | I10: =H10&".0-255" -> .0-255
A11: =_xlfn.XLOOKUP(B11,Summary!B:B,Summary!C:C,"") -> Whatsminer M60S | B11: C241 | C11: 10.31.36 | D11: 10.31.37 | E11: 10.31.38 | F11: 10.31.39 | I11: =H11&".0-255" -> .0-255
A12: =_xlfn.XLOOKUP(B12,Summary!B:B,Summary!C:C,"") -> Whatsminer M60S | B12: C242 | C12: 10.31.40 | D12: 10.31.41 | E12: 10.31.42 | F12: 10.31.43 | I12: =H12&".0-255" -> .0-255
A13: =_xlfn.XLOOKUP(B13,Summary!B:B,Summary!C:C,"") -> Empty | B13: C243 | C13: 10.31.44 | D13: 10.31.45 | E13: 10.31.46 | F13: 10.31.47 | I13: =H13&".0-255" -> .0-255
... A54: =_xlfn.XLOOKUP(B54,Summary!B:B,Summary!C:C,"") -> Whatsminer M60 / M60S | B54: C284 | C54: 10.31.208 | D54: 10.31.209 | E54: 10.31.210 | F54: 10.31.211 | I54: =H54&".0-255" -> .0-255
I55: =H55&".0-255" -> .0-255
I56: =H56&".0-255" -> .0-255
I57: =H57&".0-255" -> .0-255
I58: =H58&".0-255" -> .0-255
I59: =H59&".0-255" -> .0-255
I60: =H60&".0-255" -> .0-255
I61: =H61&".0-255" -> .0-255
I62: =H62&".0-255" -> .0-255
I63: =H63&".0-255" -> .0-255
I64: =H64&".0-255" -> .0-255
I65: =H65&".0-255" -> .0-255
I66: =H66&".0-255" -> .0-255
... I332: =H332&".0-255" -> .0-255

Sheet IP Ranges - Immersion
A1: Miner Type | B1: Container | C1: Main Switch | D1: Tank 1 | E1: Tank 2 | F1: Tank 3 | G1: Tank 4 | H1: Tank 5 | I1: Tank 6 | J1: Tank 7 | K1: Tank 8 | L1: Phase | M1: LEGEND | P1: Power Target | Q1: Stock Power
A2: =_xlfn.XLOOKUP(B2,Summary!B:B,Summary!C:C,"") -> Mara T2 | B2: *TP01 | C2: 10.21.255.186 | D2: 10.29.11.0 | E2: 10.29.12.0 | F2: 10.29.13.0 | G2: 10.29.14.0 | H2: 10.29.15.0 | I2: 10.29.16.0 | J2: 10.29.17.0 | K2: 10.29.18.0 | L2: =_xlfn.XLOOKUP(B2,Summary!B:B,Summary!G:G) -> 0
A3: =_xlfn.XLOOKUP(B3,Summary!B:B,Summary!C:C,"") -> Whatsminer M63S | B3: *TP02 | D3: 10.21.227.0 | L3: =_xlfn.XLOOKUP(B3,Summary!B:B,Summary!G:G) -> 0
A4: =_xlfn.XLOOKUP(B4,Summary!B:B,Summary!C:C,"") -> Mara T2 | B4: C000 | C4: 10.21.255.0 | D4: 10.21.221.0 | E4: --- | F4: --- | G4: ---| | H4: 10.21.222.0 | I4: --- | J4: --- | K4: ---| | L4: =_xlfn.XLOOKUP(B4,Summary!B:B,Summary!G:G) -> 0
A5: =_xlfn.XLOOKUP(B5,Summary!B:B,Summary!C:C,"") -> Teraflux AI3680 | B5: C001 | C5: 10.21.255.1 | D5: 10.21.11.0 | E5: --- | F5: --- | G5: ---| | H5: 10.21.12.0 | I5: --- | J5: --- | K5: ---| | L5: =_xlfn.XLOOKUP(B5,Summary!B:B,Summary!G:G) -> 0 | M5: Phase 0 | N5: Pickaxe 2
A6: =_xlfn.XLOOKUP(B6,Summary!B:B,Summary!C:C,"") -> Teraflux AI3680 | B6: C002 | C6: 10.21.255.2 | D6: 10.21.13.0 | E6: --- | F6: --- | G6: ---| | H6: 10.21.14.0 | I6: --- | J6: --- | K6: ---| | L6: =_xlfn.XLOOKUP(B6,Summary!B:B,Summary!G:G) -> 0 | M6: Phase 1 | N6: Pickaxe 2
A7: =_xlfn.XLOOKUP(B7,Summary!B:B,Summary!C:C,"") -> BixBit Hydro | B7: C003 | C7: 10.21.255.3 | D7: 10.21.15.0 | E7: --- | F7: --- | G7: ---| | H7: 10.21.16.0 | I7: --- | J7: --- | K7: ---| | L7: =_xlfn.XLOOKUP(B7,Summary!B:B,Summary!G:G) -> 0 | M7: Phase 1+ | N7: Pickaxe 2
A8: =_xlfn.XLOOKUP(B8,Summary!B:B,Summary!C:C,"") -> Whatsminer M56S++ | B8: C004 | C8: 10.21.255.4 | D8: 10.21.17.0 | E8: --- | F8: --- | G8: ---| | H8: 10.21.18.0 | I8: --- | J8: --- | K8: ---| | L8: =_xlfn.XLOOKUP(B8,Summary!B:B,Summary!G:G) -> 1 | M8: Phase 2 | N8: Pickaxe 2 | P8: Stock | Q8: 5700W
A9: =_xlfn.XLOOKUP(B9,Summary!B:B,Summary!C:C,"") -> Whatsminer M56S++ | B9: C005 | C9: 10.21.255.5 | D9: 10.21.51.0 | E9: 10.21.52.0 | F9: 10.21.53.0 | G9: 10.21.54.0 | H9: 10.21.55.0 | I9: 10.21.56.0 | J9: 10.21.57.0 | K9: 10.21.58.0 | L9: =_xlfn.XLOOKUP(B9,Summary!B:B,Summary!G:G) -> 1 | M9: Phase 3 | N9: Pickaxe 2 | P9: Stock | Q9: 5700W
A10: =_xlfn.XLOOKUP(B10,Summary!B:B,Summary!C:C,"") -> Whatsminer M56S++ | B10: C006 | C10: 10.21.255.6 | D10: 10.21.61.0 | E10: 10.21.62.0 | F10: 10.21.63.0 | G10: 10.21.64.0 | H10: 10.21.65.0 | I10: 10.21.66.0 | J10: 10.21.67.0 | K10: 10.21.68.0 | L10: =_xlfn.XLOOKUP(B10,Summary!B:B,Summary!G:G) -> 1 | M10: Phase 4 | N10: Pickaxe 3 | P10: Stock | Q10: 5700W
A11: =_xlfn.XLOOKUP(B11,Summary!B:B,Summary!C:C,"") -> Whatsminer M56S++ | B11: C007 | C11: 10.21.255.7 | D11: 10.21.71.0 | E11: 10.21.72.0 | F11: 10.21.73.0 | G11: 10.21.74.0 | H11: 10.21.75.0 | I11: 10.21.76.0 | J11: 10.21.77.0 | K11: 10.21.78.0 | L11: =_xlfn.XLOOKUP(B11,Summary!B:B,Summary!G:G) -> 1 | M11: Phase 5 | N11: Pickaxe 3 | P11: Stock | Q11: 5700W
A12: =_xlfn.XLOOKUP(B12,Summary!B:B,Summary!C:C,"") -> Whatsminer M56S++ | B12: C008 | C12: 10.21.255.8 | D12: 10.21.81.0 | E12: 10.21.82.0 | F12: 10.21.83.0 | G12: 10.21.84.0 | H12: 10.21.85.0 | I12: 10.21.86.0 | J12: 10.21.87.0 | K12: 10.21.88.0 | L12: =_xlfn.XLOOKUP(B12,Summary!B:B,Summary!G:G) -> 1 | M12: Phase 6 | N12: Pickaxe 3 | P12: Stock | Q12: 5700W
A13: =_xlfn.XLOOKUP(B13,Summary!B:B,Summary!C:C,"") -> Whatsminer M56S++ | B13: C009 | C13: 10.21.255.9 | D13: 10.21.91.0 | E13: 10.21.92.0 | F13: 10.21.93.0 | G13: 10.21.94.0 | H13: 10.21.95.0 | I13: 10.21.96.0 | J13: 10.21.97.0 | K13: 10.21.98.0 | L13: =_xlfn.XLOOKUP(B13,Summary!B:B,Summary!G:G) -> 1 | P13: Stock | Q13: 5700W
A14: =_xlfn.XLOOKUP(B14,Summary!B:B,Summary!C:C,"") -> Whatsminer M56S++ | B14: C010 | C14: 10.21.255.10 | D14: 10.21.101.0 | E14: 10.21.102.0 | F14: 10.21.103.0 | G14: 10.21.104.0 | H14: 10.21.105.0 | I14: 10.21.106.0 | J14: 10.21.107.0 | K14: 10.21.108.0 | L14: =_xlfn.XLOOKUP(B14,Summary!B:B,Summary!G:G) -> 1+ | P14: Stock | Q14: 5700W
A15: =_xlfn.XLOOKUP(B15,Summary!B:B,Summary!C:C,"") -> Whatsminer M56S++ | B15: C011 | C15: 10.21.255.11 | D15: 10.21.111.0 | E15: 10.21.112.0 | F15: 10.21.113.0 | G15: 10.21.114.0 | H15: 10.21.115.0 | I15: 10.21.116.0 | J15: 10.21.117.0 | K15: 10.21.118.0 | L15: =_xlfn.XLOOKUP(B15,Summary!B:B,Summary!G:G) -> 1+ | P15: Stock | Q15: 5700W
A16: =_xlfn.XLOOKUP(B16,Summary!B:B,Summary!C:C,"") -> Whatsminer M56S++ | B16: C012 | C16: 10.21.255.12 | D16: 10.21.121.0 | E16: 10.21.122.0 | F16: 10.21.123.0 | G16: 10.21.124.0 | H16: 10.21.125.0 | I16: 10.21.126.0 | J16: 10.21.127.0 | K16: 10.21.128.0 | L16: =_xlfn.XLOOKUP(B16,Summary!B:B,Summary!G:G) -> 1+ | P16: Stock | Q16: 5700W
A17: =_xlfn.XLOOKUP(B17,Summary!B:B,Summary!C:C,"") -> Whatsminer M66S | B17: C013 | C17: 10.21.255.13 | D17: 10.21.41.0 | E17: --- | F17: --- | G17: ---| | H17: 10.21.42.0 | I17: --- | J17: --- | K17: ---| | L17: =_xlfn.XLOOKUP(B17,Summary!B:B,Summary!G:G) -> 1+ | O17: =N17&"-255" -> -255 | P17: Stock | Q17: 5700W
A18: =_xlfn.XLOOKUP(B18,Summary!B:B,Summary!C:C,"") -> Greenhash Hydro | B18: C014 | C18: 10.21.255.14 | D18: 10.21.43.0 | E18: --- | F18: --- | G18: ---| | H18: 10.21.44.0 | I18: --- | J18: --- | K18: ---| | L18: =_xlfn.XLOOKUP(B18,Summary!B:B,Summary!G:G) -> 0 | O18: =N18&"-255" -> -255
A19: =_xlfn.XLOOKUP(B19,Summary!B:B,Summary!C:C,"") -> Fog Hashing Hydro | B19: C015 | C19: 10.21.255.15 | D19: 10.22.21.0 | E19: 10.22.22.0 | F19: 10.22.23.0 | G19: 10.22.24.0 | H19: 10.22.25.0 | I19: 10.22.26.0 | J19: 10.22.27.0 | K19: 10.22.28.0 | L19: =_xlfn.XLOOKUP(B19,Summary!B:B,Summary!G:G) -> 0 | O19: =N19&"-255" -> -255
A20: =_xlfn.XLOOKUP(B20,Summary!B:B,Summary!C:C,"") -> Fbox Hydro | B20: C016 | C20: 10.21.255.16 | D20: 10.22.31.0 | E20: 10.22.32.0 | F20: 10.22.33.0 | G20: 10.22.34.0 | H20: 10.22.35.0 | I20: x | J20: x | K20: x | L20: =_xlfn.XLOOKUP(B20,Summary!B:B,Summary!G:G) -> 0 | O20: =N20&"-255" -> -255 | U20: C016 | V20: 10.21.255.16 | W20: 10.21.47.0 | X20: --- | Y20: --- | Z20: ---| | AA20: 10.21.48.0 | AB20: --- | AC20: --- | AD20: ---|
A21: =_xlfn.XLOOKUP(B21,Summary!B:B,Summary!C:C,"") -> Antminer S21 | B21: C017 | C21: 10.21.255.17 | D21: 10.22.41.0 | E21: 10.22.42.0 | F21: 10.22.43.0 | G21: 10.22.44.0 | H21: 10.22.45.0 | I21: 10.22.46.0 | J21: 10.22.47.0 | K21: 10.22.48.0 | L21: =_xlfn.XLOOKUP(B21,Summary!B:B,Summary!G:G) -> 0 | O21: =N21&"-255" -> -255 | P21: 4800W | Q21: 3800W
A22: =_xlfn.XLOOKUP(B22,Summary!B:B,Summary!C:C,"") -> Whatsminer M56S++ | B22: C018 | C22: 10.21.255.18 | D22: 10.22.51.0 | E22: 10.22.52.0 | F22: 10.22.53.0 | G22: 10.22.54.0 | H22: 10.22.55.0 | I22: 10.22.56.0 | J22: 10.22.57.0 | K22: 10.22.58.0 | L22: =_xlfn.XLOOKUP(B22,Summary!B:B,Summary!G:G) -> 1 | O22: =N22&"-255" -> -255 | P22: Stock | Q22: 5700W
A23: =_xlfn.XLOOKUP(B23,Summary!B:B,Summary!C:C,"") -> Whatsminer M56S++ | B23: C019 | C23: 10.21.255.19 | D23: 10.22.61.0 | E23: 10.22.62.0 | F23: 10.22.63.0 | G23: 10.22.64.0 | H23: 10.22.65.0 | I23: 10.22.66.0 | J23: 10.22.67.0 | K23: 10.22.68.0 | L23: =_xlfn.XLOOKUP(B23,Summary!B:B,Summary!G:G) -> 1 | O23: =N23&"-255" -> -255 | P23: Stock | Q23: 5700W
A24: =_xlfn.XLOOKUP(B24,Summary!B:B,Summary!C:C,"") -> Whatsminer M56S++ | B24: C020 | C24: 10.21.255.20 | D24: 10.22.71.0 | E24: 10.22.72.0 | F24: 10.22.73.0 | G24: 10.22.74.0 | H24: 10.22.75.0 | I24: 10.22.76.0 | J24: 10.22.77.0 | K24: 10.22.78.0 | L24: =_xlfn.XLOOKUP(B24,Summary!B:B,Summary!G:G) -> 1 | O24: =N24&"-255" -> -255 | P24: Stock | Q24: 5700W
A25: =_xlfn.XLOOKUP(B25,Summary!B:B,Summary!C:C,"") -> Whatsminer M56S++ | B25: C021 | C25: 10.21.255.21 | D25: 10.22.81.0 | E25: 10.22.82.0 | F25: 10.22.83.0 | G25: 10.22.84.0 | H25: 10.22.85.0 | I25: 10.22.86.0 | J25: 10.22.87.0 | K25: 10.22.88.0 | L25: =_xlfn.XLOOKUP(B25,Summary!B:B,Summary!G:G) -> 1 | O25: =N25&"-255" -> -255 | P25: Stock | Q25: 5700W
A26: =_xlfn.XLOOKUP(B26,Summary!B:B,Summary!C:C,"") -> Whatsminer M56S++ | B26: C022 | C26: 10.21.255.22 | D26: 10.22.91.0 | E26: 10.22.92.0 | F26: 10.22.93.0 | G26: 10.22.94.0 | H26: 10.22.95.0 | I26: 10.22.96.0 | J26: 10.22.97.0 | K26: 10.22.98.0 | L26: =_xlfn.XLOOKUP(B26,Summary!B:B,Summary!G:G) -> 1 | O26: =N26&"-255" -> -255 | P26: Stock | Q26: 5700W
A27: =_xlfn.XLOOKUP(B27,Summary!B:B,Summary!C:C,"") -> Whatsminer M56S++ | B27: C023 | C27: 10.21.255.23 | D27: 10.22.101.0 | E27: 10.22.102.0 | F27: 10.22.103.0 | G27: 10.22.104.0 | H27: 10.22.105.0 | I27: 10.22.106.0 | J27: 10.22.107.0 | K27: 10.22.108.0 | L27: =_xlfn.XLOOKUP(B27,Summary!B:B,Summary!G:G) -> 1 | O27: =N27&"-255" -> -255 | P27: Stock | Q27: 5700W
A28: =_xlfn.XLOOKUP(B28,Summary!B:B,Summary!C:C,"") -> Whatsminer M56S++ | B28: C024 | C28: 10.21.255.24 | D28: 10.22.111.0 | E28: 10.22.112.0 | F28: 10.22.113.0 | G28: 10.22.114.0 | H28: 10.22.115.0 | I28: 10.22.116.0 | J28: 10.22.117.0 | K28: 10.22.118.0 | L28: =_xlfn.XLOOKUP(B28,Summary!B:B,Summary!G:G) -> 1+ | O28: =N28&"-255" -> -255 | P28: Stock | Q28: 5700W
A29: =_xlfn.XLOOKUP(B29,Summary!B:B,Summary!C:C,"") -> Whatsminer M56S++ | B29: C025 | C29: 10.21.255.25 | D29: 10.22.121.0 | E29: 10.22.122.0 | F29: 10.22.123.0 | G29: 10.22.124.0 | H29: 10.22.125.0 | I29: 10.22.126.0 | J29: 10.22.127.0 | K29: 10.22.128.0 | L29: =_xlfn.XLOOKUP(B29,Summary!B:B,Summary!G:G) -> 1+ | O29: =N29&"-255" -> -255 | P29: Stock | Q29: 5700W
A30: =_xlfn.XLOOKUP(B30,Summary!B:B,Summary!C:C,"") -> Whatsminer M56S++ | B30: C026 | C30: 10.21.255.26 | D30: 10.22.131.0 | E30: 10.22.132.0 | F30: 10.22.133.0 | G30: 10.22.134.0 | H30: 10.22.135.0 | I30: 10.22.136.0 | J30: 10.22.137.0 | K30: 10.22.138.0 | L30: =_xlfn.XLOOKUP(B30,Summary!B:B,Summary!G:G) -> 1+ | O30: =N30&"-255" -> -255 | P30: Stock | Q30: 5700W
A31: =_xlfn.XLOOKUP(B31,Summary!B:B,Summary!C:C,"") -> Whatsminer M56S++ | B31: C027 | C31: 10.21.255.27 | D31: 10.22.141.0 | E31: 10.22.142.0 | F31: 10.22.143.0 | G31: 10.22.144.0 | H31: 10.22.145.0 | I31: 10.22.146.0 | J31: 10.22.147.0 | K31: 10.22.148.0 | L31: =_xlfn.XLOOKUP(B31,Summary!B:B,Summary!G:G) -> 1+ | O31: =N31&"-255" -> -255 | P31: Stock | Q31: 5700W
A32: =_xlfn.XLOOKUP(B32,Summary!B:B,Summary!C:C,"") -> Antminer S21 | B32: C028 | C32: 10.21.255.28 | D32: 10.23.11.0 | E32: 10.23.12.0 | F32: 10.23.13.0 | G32: 10.23.14.0 | H32: 10.23.15.0 | I32: 10.23.16.0 | J32: 10.23.17.0 | K32: 10.23.18.0 | L32: =_xlfn.XLOOKUP(B32,Summary!B:B,Summary!G:G) -> 0 | O32: =N32&"-255" -> -255 | P32: 5000W | Q32: 3800W
... A51: =_xlfn.XLOOKUP(B51,Summary!B:B,Summary!C:C,"") -> Antminer S21 | B51: C047 | C51: 10.21.255.47 | D51: 10.24.61.0 | E51: 10.24.62.0 | F51: 10.24.63.0 | G51: 10.24.64.0 | H51: 10.24.65.0 | I51: 10.24.66.0 | J51: 10.24.67.0 | K51: 10.24.68.0 | L51: =_xlfn.XLOOKUP(B51,Summary!B:B,Summary!G:G) -> 1 | O51: =N51&"-255" -> -255 | P51: Stock | Q51: 3800W
A52: =_xlfn.XLOOKUP(B52,Summary!B:B,Summary!C:C,"") -> TAE BESS | B52: C048 | C52: 10.21.255.48 | D52: 10.24.71.0 | E52: 10.24.72.0 | F52: 10.24.73.0 | G52: 10.24.74.0 | H52: 10.24.75.0 | I52: 10.24.76.0 | J52: 10.24.77.0 | K52: 10.24.78.0 | L52: =_xlfn.XLOOKUP(B52,Summary!B:B,Summary!G:G) -> 1 | O52: =N52&"-255" -> -255
A53: =_xlfn.XLOOKUP(B53,Summary!B:B,Summary!C:C,"") -> Whatsminer M56S++ | B53: C049 | C53: 10.21.255.49 | D53: 10.24.81.0 | E53: 10.24.82.0 | F53: 10.24.83.0 | G53: 10.24.84.0 | H53: 10.24.85.0 | I53: 10.24.86.0 | J53: 10.24.87.0 | K53: 10.24.88.0 | L53: =_xlfn.XLOOKUP(B53,Summary!B:B,Summary!G:G) -> 1 | O53: =N53&"-255" -> -255 | P53: Stock | Q53: 5700W
A54: =_xlfn.XLOOKUP(B54,Summary!B:B,Summary!C:C,"") -> Whatsminer M56S++ | B54: C050 | C54: 10.21.255.50 | D54: 10.24.91.0 | E54: 10.24.92.0 | F54: 10.24.93.0 | G54: 10.24.94.0 | H54: 10.24.95.0 | I54: 10.24.96.0 | J54: 10.24.97.0 | K54: 10.24.98.0 | L54: =_xlfn.XLOOKUP(B54,Summary!B:B,Summary!G:G) -> 1 | O54: =N54&"-255" -> -255 | P54: Stock | Q54: 5700W
A55: =_xlfn.XLOOKUP(B55,Summary!B:B,Summary!C:C,"") -> Whatsminer M56S++ | B55: C051 | C55: 10.21.255.51 | D55: 10.24.101.0 | E55: 10.24.102.0 | F55: 10.24.103.0 | G55: 10.24.104.0 | H55: 10.24.105.0 | I55: 10.24.106.0 | J55: 10.24.107.0 | K55: 10.24.108.0 | L55: =_xlfn.XLOOKUP(B55,Summary!B:B,Summary!G:G) -> 1 | O55: =N55&"-255" -> -255 | P55: Stock | Q55: 5700W
A56: =_xlfn.XLOOKUP(B56,Summary!B:B,Summary!C:C,"") -> Whatsminer M56S++ / M66S | B56: C052 | C56: 10.21.255.52 | D56: 10.24.111.0 | E56: 10.24.112.0 | F56: 10.24.113.0 | G56: 10.24.114.0 | H56: 10.24.115.0 | I56: 10.24.116.0 | J56: 10.24.117.0 | K56: 10.24.118.0 | L56: =_xlfn.XLOOKUP(B56,Summary!B:B,Summary!G:G) -> 1+ | O56: =N56&"-255" -> -255 | P56: Stock | Q56: 5700W
A57: =_xlfn.XLOOKUP(B57,Summary!B:B,Summary!C:C,"") -> Whatsminer M66S | B57: C053 | C57: 10.21.255.53 | D57: 10.24.121.0 | E57: 10.24.122.0 | F57: 10.24.123.0 | G57: 10.24.124.0 | H57: 10.24.125.0 | I57: 10.24.126.0 | J57: 10.24.127.0 | K57: 10.24.128.0 | L57: =_xlfn.XLOOKUP(B57,Summary!B:B,Summary!G:G) -> 1+ | O57: =N57&"-255" -> -255 | P57: Stock | Q57: 5700W
A58: =_xlfn.XLOOKUP(B58,Summary!B:B,Summary!C:C,"") -> Antminer S21 | B58: C054 | C58: 10.21.255.54 | D58: 10.24.131.0 | E58: 10.24.132.0 | F58: 10.24.133.0 | G58: 10.24.134.0 | H58: 10.24.135.0 | I58: 10.24.136.0 | J58: 10.24.137.0 | K58: 10.24.138.0 | L58: =_xlfn.XLOOKUP(B58,Summary!B:B,Summary!G:G) -> 1+ | O58: =N58&"-255" -> -255 | P58: Stock | Q58: 3800W
A59: =_xlfn.XLOOKUP(B59,Summary!B:B,Summary!C:C,"") -> Antminer S21 | B59: C055 | C59: 10.21.255.55 | D59: 10.24.141.0 | E59: 10.24.142.0 | F59: 10.24.143.0 | G59: 10.24.144.0 | H59: 10.24.145.0 | I59: 10.24.146.0 | J59: 10.24.147.0 | K59: 10.24.148.0 | L59: =_xlfn.XLOOKUP(B59,Summary!B:B,Summary!G:G) -> 1+ | O59: =N59&"-255" -> -255 | P59: Stock | Q59: 3800W
A60: =_xlfn.XLOOKUP(B60,Summary!B:B,Summary!C:C,"") -> Antminer S21 | B60: C056 | C60: 10.21.255.56 | D60: 10.21.141.0 | E60: 10.21.142.0 | F60: 10.21.143.0 | G60: 10.21.144.0 | H60: 10.21.145.0 | I60: 10.21.146.0 | J60: 10.21.147.0 | K60: 10.21.148.0 | L60: =_xlfn.XLOOKUP(B60,Summary!B:B,Summary!G:G) -> 1+ | O60: =N60&"-255" -> -255 | P60: Stock | Q60: 3800W
A61: =_xlfn.XLOOKUP(B61,Summary!B:B,Summary!C:C,"") -> Antminer S21 | B61: C057 | C61: 10.21.255.57 | D61: 10.21.151.0 | E61: 10.21.152.0 | F61: 10.21.153.0 | G61: 10.21.154.0 | H61: 10.21.155.0 | I61: 10.21.156.0 | J61: 10.21.157.0 | K61: 10.21.158.0 | L61: =_xlfn.XLOOKUP(B61,Summary!B:B,Summary!G:G) -> 1+ | O61: =N61&"-255" -> -255 | P61: Stock | Q61: 3800W
A62: =_xlfn.XLOOKUP(B62,Summary!B:B,Summary!C:C,"") -> Antminer S21 | B62: C058 | C62: 10.21.255.58 | D62: 10.21.161.0 | E62: 10.21.162.0 | F62: 10.21.163.0 | G62: 10.21.164.0 | H62: 10.21.165.0 | I62: 10.21.166.0 | J62: 10.21.167.0 | K62: 10.21.168.0 | L62: =_xlfn.XLOOKUP(B62,Summary!B:B,Summary!G:G) -> 1+ | O62: =N62&"-255" -> -255 | P62: Stock | Q62: 3800W
A63: =_xlfn.XLOOKUP(B63,Summary!B:B,Summary!C:C,"") -> Antminer S21 | B63: C059 | C63: 10.21.255.59 | D63: 10.21.171.0 | E63: 10.21.172.0 | F63: 10.21.173.0 | G63: 10.21.174.0 | H63: 10.21.175.0 | I63: 10.21.176.0 | J63: 10.21.177.0 | K63: 10.21.178.0 | L63: =_xlfn.XLOOKUP(B63,Summary!B:B,Summary!G:G) -> 1+ | O63: =N63&"-255" -> -255 | P63: Stock | Q63: 3800W
A64: =_xlfn.XLOOKUP(B64,Summary!B:B,Summary!C:C,"") -> Antminer S21 | B64: C060 | C64: 10.21.255.60 | D64: 10.22.151.0 | E64: 10.22.152.0 | F64: 10.22.153.0 | G64: 10.22.154.0 | H64: 10.22.155.0 | I64: 10.22.156.0 | J64: 10.22.157.0 | K64: 10.22.158.0 | L64: =_xlfn.XLOOKUP(B64,Summary!B:B,Summary!G:G) -> 1+ | O64: =N64&"-255" -> -255 | P64: Stock | Q64: 3800W
... A131: =_xlfn.XLOOKUP(B131,Summary!B:B,Summary!C:C,"") -> Antminer S21 | B131: C127 | C131: 10.21.255.127 | D131: 10.26.141.0 | E131: 10.26.142.0 | F131: 10.26.143.0 | G131: 10.26.144.0 | H131: 10.26.145.0 | I131: 10.26.146.0 | J131: 10.26.147.0 | K131: 10.26.148.0 | L131: =_xlfn.XLOOKUP(B131,Summary!B:B,Summary!G:G) -> 3 | O131: =N131&"-255" -> -255 | P131: 4200W | Q131: 3800W
A132: =_xlfn.XLOOKUP(B132,Summary!B:B,Summary!C:C,"") -> Antminer S21 | B132: C128 | C132: 10.21.255.128 | D132: 10.26.151.0 | E132: 10.26.152.0 | F132: 10.26.153.0 | G132: 10.26.154.0 | H132: 10.26.155.0 | I132: 10.26.156.0 | J132: 10.26.157.0 | K132: 10.26.158.0 | L132: =_xlfn.XLOOKUP(B132,Summary!B:B,Summary!G:G) -> 4 | O132: =N132&"-255" -> -255 | P132: 4400W | Q132: 3800W | S132: LEAVE ON STOCK POWER UNTIL XF REPAIR
A133: =_xlfn.XLOOKUP(B133,Summary!B:B,Summary!C:C,"") -> Antminer S21 | B133: C129 | C133: 10.21.255.129 | D133: 10.26.161.0 | E133: 10.26.162.0 | F133: 10.26.163.0 | G133: 10.26.164.0 | H133: 10.26.165.0 | I133: 10.26.166.0 | J133: 10.26.167.0 | K133: 10.26.168.0 | L133: =_xlfn.XLOOKUP(B133,Summary!B:B,Summary!G:G) -> 4 | O133: =N133&"-255" -> -255 | P133: 4400W | Q133: 3800W | R133: LEAVE ON STOCK POWER UNTIL XF REPAIR | S133: LEAVE ON STOCK POWER UNTIL XF REPAIR
A134: =_xlfn.XLOOKUP(B134,Summary!B:B,Summary!C:C,"") -> Antminer S21 | B134: C130 | C134: 10.21.255.130 | D134: 10.26.171.0 | E134: 10.26.172.0 | F134: 10.26.173.0 | G134: 10.26.174.0 | H134: 10.26.175.0 | I134: 10.26.176.0 | J134: 10.26.177.0 | K134: 10.26.178.0 | L134: =_xlfn.XLOOKUP(B134,Summary!B:B,Summary!G:G) -> 4 | O134: =N134&"-255" -> -255 | P134: 4400W | Q134: 3800W
A135: =_xlfn.XLOOKUP(B135,Summary!B:B,Summary!C:C,"") -> Antminer S21 | B135: C131 | C135: 10.21.255.131 | D135: 10.26.181.0 | E135: 10.26.182.0 | F135: 10.26.183.0 | G135: 10.26.184.0 | H135: 10.26.185.0 | I135: 10.26.186.0 | J135: 10.26.187.0 | K135: 10.26.188.0 | L135: =_xlfn.XLOOKUP(B135,Summary!B:B,Summary!G:G) -> 4 | O135: =N135&"-255" -> -255 | P135: 4400W | Q135: 3800W
A136: =_xlfn.XLOOKUP(B136,Summary!B:B,Summary!C:C,"") -> Antminer S21 | B136: C132 | C136: 10.21.255.132 | D136: 10.26.191.0 | E136: 10.26.192.0 | F136: 10.26.193.0 | G136: 10.26.194.0 | H136: 10.26.195.0 | I136: 10.26.196.0 | J136: 10.26.197.0 | K136: 10.26.198.0 | L136: =_xlfn.XLOOKUP(B136,Summary!B:B,Summary!G:G) -> 4 | O136: =N136&"-255" -> -255 | P136: 4400W | Q136: 3800W
A137: =_xlfn.XLOOKUP(B137,Summary!B:B,Summary!C:C,"") -> Antminer S21 | B137: C133 | C137: 10.21.255.133 | D137: 10.26.201.0 | E137: 10.26.202.0 | F137: 10.26.203.0 | G137: 10.26.204.0 | H137: 10.26.205.0 | I137: 10.26.206.0 | J137: 10.26.207.0 | K137: 10.26.208.0 | L137: =_xlfn.XLOOKUP(B137,Summary!B:B,Summary!G:G) -> 4 | O137: =N137&"-255" -> -255 | P137: 4400W | Q137: 3800W
A138: =_xlfn.XLOOKUP(B138,Summary!B:B,Summary!C:C,"") -> Antminer S21 | B138: C134 | C138: 10.21.255.134 | D138: 10.26.211.0 | E138: 10.26.212.0 | F138: 10.26.213.0 | G138: 10.26.214.0 | H138: 10.26.215.0 | I138: 10.26.216.0 | J138: 10.26.217.0 | K138: 10.26.218.0 | L138: =_xlfn.XLOOKUP(B138,Summary!B:B,Summary!G:G) -> 4 | O138: =N138&"-255" -> -255 | P138: 4400W | Q138: 3800W
A139: =_xlfn.XLOOKUP(B139,Summary!B:B,Summary!C:C,"") -> Antminer S21 | B139: C135 | C139: 10.21.255.135 | D139: 10.26.221.0 | E139: 10.26.222.0 | F139: 10.26.223.0 | G139: 10.26.224.0 | H139: 10.26.225.0 | I139: 10.26.226.0 | J139: 10.26.227.0 | K139: 10.26.228.0 | L139: =_xlfn.XLOOKUP(B139,Summary!B:B,Summary!G:G) -> 4 | O139: =N139&"-255" -> -255 | P139: 4400W | Q139: 3800W
A140: =_xlfn.XLOOKUP(B140,Summary!B:B,Summary!C:C,"") -> Antminer S21 | B140: C136 | C140: 10.21.255.136 | D140: 10.26.231.0 | E140: 10.26.232.0 | F140: 10.26.233.0 | G140: 10.26.234.0 | H140: 10.26.235.0 | I140: 10.26.236.0 | J140: 10.26.237.0 | K140: 10.26.238.0 | L140: =_xlfn.XLOOKUP(B140,Summary!B:B,Summary!G:G) -> 4 | O140: =N140&"-255" -> -255 | P140: 4400W | Q140: 3800W
A141: =_xlfn.XLOOKUP(B141,Summary!B:B,Summary!C:C,"") -> Antminer S21 | B141: C137 | C141: 10.21.255.137 | D141: 10.26.241.0 | E141: 10.26.242.0 | F141: 10.26.243.0 | G141: 10.26.244.0 | H141: 10.26.245.0 | I141: 10.26.246.0 | J141: 10.26.247.0 | K141: 10.26.248.0 | L141: =_xlfn.XLOOKUP(B141,Summary!B:B,Summary!G:G) -> 4 | O141: =N141&"-255" -> -255 | P141: 4400W | Q141: 3800W
A142: =_xlfn.XLOOKUP(B142,Summary!B:B,Summary!C:C,"") -> Antminer S21 | B142: C138 | C142: 10.21.255.138 | D142: 10.27.11.0 | E142: 10.27.12.0 | F142: 10.27.13.0 | G142: 10.27.14.0 | H142: 10.27.15.0 | I142: 10.27.16.0 | J142: 10.27.17.0 | K142: 10.27.18.0 | L142: =_xlfn.XLOOKUP(B142,Summary!B:B,Summary!G:G) -> 4 | O142: =N142&"-255" -> -255 | P142: 4400W | Q142: 3800W
A143: =_xlfn.XLOOKUP(B143,Summary!B:B,Summary!C:C,"") -> Antminer S21 | B143: C139 | C143: 10.21.255.139 | D143: 10.27.21.0 | E143: 10.27.22.0 | F143: 10.27.23.0 | G143: 10.27.24.0 | H143: 10.27.25.0 | I143: 10.27.26.0 | J143: 10.27.27.0 | K143: 10.27.28.0 | L143: =_xlfn.XLOOKUP(B143,Summary!B:B,Summary!G:G) -> 4 | O143: =N143&"-255" -> -255 | P143: 4400W | Q143: 3800W
A144: =_xlfn.XLOOKUP(B144,Summary!B:B,Summary!C:C,"") -> Antminer S21 | B144: C140 | C144: 10.21.255.140 | D144: 10.27.31.0 | E144: 10.27.32.0 | F144: 10.27.33.0 | G144: 10.27.34.0 | H144: 10.27.35.0 | I144: 10.27.36.0 | J144: 10.27.37.0 | K144: 10.27.38.0 | L144: =_xlfn.XLOOKUP(B144,Summary!B:B,Summary!G:G) -> 4 | O144: =N144&"-255" -> -255 | P144: 4400W | Q144: 3800W
A145: =_xlfn.XLOOKUP(B145,Summary!B:B,Summary!C:C,"") -> Antminer S21 | B145: C141 | C145: 10.21.255.141 | D145: 10.27.41.0 | E145: 10.27.42.0 | F145: 10.27.43.0 | G145: 10.27.44.0 | H145: 10.27.45.0 | I145: 10.27.46.0 | J145: 10.27.47.0 | K145: 10.27.48.0 | L145: =_xlfn.XLOOKUP(B145,Summary!B:B,Summary!G:G) -> 4 | O145: =N145&"-255" -> -255 | P145: 4400W | Q145: 3800W
... A159: =_xlfn.XLOOKUP(B159,Summary!B:B,Summary!C:C,"") -> Antminer S21 | B159: C155 | C159: 10.21.255.155 | D159: 10.27.181.0 | E159: 10.27.182.0 | F159: 10.27.183.0 | G159: 10.27.184.0 | H159: 10.27.185.0 | I159: 10.27.186.0 | J159: 10.27.187.0 | K159: 10.27.188.0 | L159: =_xlfn.XLOOKUP(B159,Summary!B:B,Summary!G:G) -> 4 | O159: =N159&"-255" -> -255 | P159: 4400W | Q159: 3800W
A160: =_xlfn.XLOOKUP(B160,Summary!B:B,Summary!C:C,"") -> Antminer S21 | B160: C156 | C160: 10.21.255.156 | D160: 10.27.191.0 | E160: 10.27.192.0 | F160: 10.27.193.0 | G160: 10.27.194.0 | H160: 10.27.195.0 | I160: 10.27.196.0 | J160: 10.27.197.0 | K160: 10.27.198.0 | L160: =_xlfn.XLOOKUP(B160,Summary!B:B,Summary!G:G) -> 4 | O160: =N160&"-255" -> -255 | P160: 4400W | Q160: 3800W | S160: LEAVE ON STOCK POWER UNTIL XF REPAIR
A161: =_xlfn.XLOOKUP(B161,Summary!B:B,Summary!C:C,"") -> Antminer S21 | B161: C157 | C161: 10.21.255.157 | D161: 10.27.201.0 | E161: 10.27.202.0 | F161: 10.27.203.0 | G161: 10.27.204.0 | H161: 10.27.205.0 | I161: 10.27.206.0 | J161: 10.27.207.0 | K161: 10.27.208.0 | L161: =_xlfn.XLOOKUP(B161,Summary!B:B,Summary!G:G) -> 4 | O161: =N161&"-255" -> -255 | P161: 4400W | Q161: 3800W | S161: LEAVE ON STOCK POWER UNTIL XF REPAIR
A162: =_xlfn.XLOOKUP(B162,Summary!B:B,Summary!C:C,"") -> Antminer S21 | B162: C158 | C162: 10.21.255.158 | D162: 10.27.211.0 | E162: 10.27.212.0 | F162: 10.27.213.0 | G162: 10.27.214.0 | H162: 10.27.215.0 | I162: 10.27.216.0 | J162: 10.27.217.0 | K162: 10.27.218.0 | L162: =_xlfn.XLOOKUP(B162,Summary!B:B,Summary!G:G) -> 4 | O162: =N162&"-255" -> -255 | P162: 4400W | Q162: 3800W
A163: =_xlfn.XLOOKUP(B163,Summary!B:B,Summary!C:C,"") -> Antminer S21 | B163: C159 | C163: 10.21.255.159 | D163: 10.27.221.0 | E163: 10.27.222.0 | F163: 10.27.223.0 | G163: 10.27.224.0 | H163: 10.27.225.0 | I163: 10.27.226.0 | J163: 10.27.227.0 | K163: 10.27.228.0 | L163: =_xlfn.XLOOKUP(B163,Summary!B:B,Summary!G:G) -> 4 | O163: =N163&"-255" -> -255 | P163: 4400W | Q163: 3800W
A164: =_xlfn.XLOOKUP(B164,Summary!B:B,Summary!C:C,"") -> Antminer S21 | B164: C160 | C164: 10.21.255.160 | D164: 10.27.231.0 | E164: 10.27.232.0 | F164: 10.27.233.0 | G164: 10.27.234.0 | H164: 10.27.235.0 | I164: 10.27.236.0 | J164: 10.27.237.0 | K164: 10.27.238.0 | L164: =_xlfn.XLOOKUP(B164,Summary!B:B,Summary!G:G) -> 4 | O164: =N164&"-255" -> -255 | P164: 4400W | Q164: 3800W | S164: LEAVE ON STOCK POWER UNTIL XF REPAIR
A165: =_xlfn.XLOOKUP(B165,Summary!B:B,Summary!C:C,"") -> Antminer S21 | B165: C161 | C165: 10.21.255.161 | D165: 10.27.241.0 | E165: 10.27.242.0 | F165: 10.27.243.0 | G165: 10.27.244.0 | H165: 10.27.245.0 | I165: 10.27.246.0 | J165: 10.27.247.0 | K165: 10.27.248.0 | L165: =_xlfn.XLOOKUP(B165,Summary!B:B,Summary!G:G) -> 4 | O165: =N165&"-255" -> -255 | P165: 4400W | Q165: 3800W | S165: LEAVE ON STOCK POWER UNTIL XF REPAIR
A166: =_xlfn.XLOOKUP(B166,Summary!B:B,Summary!C:C,"") -> Antminer S21 | B166: C162 | C166: 10.21.255.162 | D166: 10.28.11.0 | E166: 10.28.12.0 | F166: 10.28.13.0 | G166: 10.28.14.0 | H166: 10.28.15.0 | I166: 10.28.16.0 | J166: 10.28.17.0 | K166: 10.28.18.0 | L166: =_xlfn.XLOOKUP(B166,Summary!B:B,Summary!G:G) -> 4 | O166: =N166&"-255" -> -255 | P166: 4400W | Q166: 3800W
A167: =_xlfn.XLOOKUP(B167,Summary!B:B,Summary!C:C,"") -> Antminer S21 | B167: C163 | C167: 10.21.255.163 | D167: 10.28.21.0 | E167: 10.28.22.0 | F167: 10.28.23.0 | G167: 10.28.24.0 | H167: 10.28.25.0 | I167: 10.28.26.0 | J167: 10.28.27.0 | K167: 10.28.28.0 | L167: =_xlfn.XLOOKUP(B167,Summary!B:B,Summary!G:G) -> 4 | O167: =N167&"-255" -> -255 | P167: 4400W | Q167: 3800W
A168: =_xlfn.XLOOKUP(B168,Summary!B:B,Summary!C:C,"") -> Antminer S21 | B168: C164 | C168: 10.21.255.164 | D168: 10.28.31.0 | E168: 10.28.32.0 | F168: 10.28.33.0 | G168: 10.28.34.0 | H168: 10.28.35.0 | I168: 10.28.36.0 | J168: 10.28.37.0 | K168: 10.28.38.0 | L168: =_xlfn.XLOOKUP(B168,Summary!B:B,Summary!G:G) -> 4 | O168: =N168&"-255" -> -255 | P168: 4400W | Q168: 3800W
A169: =_xlfn.XLOOKUP(B169,Summary!B:B,Summary!C:C,"") -> Antminer S21 | B169: C165 | C169: 10.21.255.165 | D169: 10.28.41.0 | E169: 10.28.42.0 | F169: 10.28.43.0 | G169: 10.28.44.0 | H169: 10.28.45.0 | I169: 10.28.46.0 | J169: 10.28.47.0 | K169: 10.28.48.0 | L169: =_xlfn.XLOOKUP(B169,Summary!B:B,Summary!G:G) -> 4 | O169: =N169&"-255" -> -255 | P169: 4400W | Q169: 3800W
A170: =_xlfn.XLOOKUP(B170,Summary!B:B,Summary!C:C,"") -> Antminer S21 | B170: C166 | C170: 10.21.255.166 | D170: 10.28.51.0 | E170: 10.28.52.0 | F170: 10.28.53.0 | G170: 10.28.54.0 | H170: 10.28.55.0 | I170: 10.28.56.0 | J170: 10.28.57.0 | K170: 10.28.58.0 | L170: =_xlfn.XLOOKUP(B170,Summary!B:B,Summary!G:G) -> 4 | O170: =N170&"-255" -> -255 | P170: 4400W | Q170: 3800W
A171: =_xlfn.XLOOKUP(B171,Summary!B:B,Summary!C:C,"") -> Antminer S21 | B171: C167 | C171: 10.21.255.167 | D171: 10.28.61.0 | E171: 10.28.62.0 | F171: 10.28.63.0 | G171: 10.28.64.0 | H171: 10.28.65.0 | I171: 10.28.66.0 | J171: 10.28.67.0 | K171: 10.28.68.0 | L171: =_xlfn.XLOOKUP(B171,Summary!B:B,Summary!G:G) -> 4 | O171: =N171&"-255" -> -255 | P171: 4400W | Q171: 3800W
A172: =_xlfn.XLOOKUP(B172,Summary!B:B,Summary!C:C,"") -> Antminer S21 | B172: C168 | C172: 10.21.255.168 | D172: 10.28.71.0 | E172: 10.28.72.0 | F172: 10.28.73.0 | G172: 10.28.74.0 | H172: 10.28.75.0 | I172: 10.28.76.0 | J172: 10.28.77.0 | K172: 10.28.78.0 | L172: =_xlfn.XLOOKUP(B172,Summary!B:B,Summary!G:G) -> 5 | O172: =N172&"-255" -> -255 | P172: Stock | Q172: 3800W
A173: =_xlfn.XLOOKUP(B173,Summary!B:B,Summary!C:C,"") -> Antminer S21 | B173: C169 | C173: 10.21.255.169 | D173: 10.28.81.0 | E173: 10.28.82.0 | F173: 10.28.83.0 | G173: 10.28.84.0 | H173: 10.28.85.0 | I173: 10.28.86.0 | J173: 10.28.87.0 | K173: 10.28.88.0 | L173: =_xlfn.XLOOKUP(B173,Summary!B:B,Summary!G:G) -> 5 | O173: =N173&"-255" -> -255 | P173: Stock | Q173: 3800W
A174: =_xlfn.XLOOKUP(B174,Summary!B:B,Summary!C:C,"") -> Antminer S21 | B174: C170 | C174: 10.21.255.170 | D174: 10.28.91.0 | E174: 10.28.92.0 | F174: 10.28.93.0 | G174: 10.28.94.0 | H174: 10.28.95.0 | I174: 10.28.96.0 | J174: 10.28.97.0 | K174: 10.28.98.0 | L174: =_xlfn.XLOOKUP(B174,Summary!B:B,Summary!G:G) -> 5 | O174: =N174&"-255" -> -255 | P174: Stock | Q174: 3800W
A175: =_xlfn.XLOOKUP(B175,Summary!B:B,Summary!C:C,"") -> Antminer S21 | B175: C171 | C175: 10.21.255.171 | D175: 10.28.101.0 | E175: 10.28.102.0 | F175: 10.28.103.0 | G175: 10.28.104.0 | H175: 10.28.105.0 | I175: 10.28.106.0 | J175: 10.28.107.0 | K175: 10.28.108.0 | L175: =_xlfn.XLOOKUP(B175,Summary!B:B,Summary!G:G) -> 5 | O175: =N175&"-255" -> -255 | P175: Stock | Q175: 3800W
A176: =_xlfn.XLOOKUP(B176,Summary!B:B,Summary!C:C,"") -> Antminer S21 | B176: C172 | C176: 10.21.255.172 | D176: 10.28.111.0 | E176: 10.28.112.0 | F176: 10.28.113.0 | G176: 10.28.114.0 | H176: 10.28.115.0 | I176: 10.28.116.0 | J176: 10.28.117.0 | K176: 10.28.118.0 | L176: =_xlfn.XLOOKUP(B176,Summary!B:B,Summary!G:G) -> 5 | O176: =N176&"-255" -> -255 | P176: Stock | Q176: 3800W
A177: =_xlfn.XLOOKUP(B177,Summary!B:B,Summary!C:C,"") -> Antminer S21 | B177: C173 | C177: 10.21.255.173 | D177: 10.28.121.0 | E177: 10.28.122.0 | F177: 10.28.123.0 | G177: 10.28.124.0 | H177: 10.28.125.0 | I177: 10.28.126.0 | J177: 10.28.127.0 | K177: 10.28.128.0 | L177: =_xlfn.XLOOKUP(B177,Summary!B:B,Summary!G:G) -> 5 | O177: =N177&"-255" -> -255 | P177: Stock | Q177: 3800W
... A189: =_xlfn.XLOOKUP(B189,Summary!B:B,Summary!C:C,"") -> Antminer S21 | B189: C185 | C189: 10.21.255.185 | D189: 10.28.241.0 | E189: 10.28.242.0 | F189: 10.28.243.0 | G189: 10.28.244.0 | H189: 10.28.245.0 | I189: 10.28.246.0 | J189: 10.28.247.0 | K189: 10.28.248.0 | L189: =_xlfn.XLOOKUP(B189,Summary!B:B,Summary!G:G) -> 5 | O189: =N189&"-255" -> -255 | P189: Stock | Q189: 3800W
A190: =_xlfn.XLOOKUP(B190,Summary!B:B,Summary!C:C,"") -> ** NOT USED ** | B190: C186 | C190: 10.21.255.186 | D190: 10.29.11.0 | E190: 10.29.12.0 | F190: 10.29.13.0 | G190: 10.29.14.0 | H190: 10.29.15.0 | I190: 10.29.16.0 | J190: 10.29.17.0 | K190: 10.29.18.0 | L190: =_xlfn.XLOOKUP(B190,Summary!B:B,Summary!G:G) -> 5 | O190: =N190&"-255" -> -255
A191: =_xlfn.XLOOKUP(B191,Summary!B:B,Summary!C:C,"") -> ** NOT USED ** | B191: C187 | C191: 10.21.255.187 | D191: 10.29.21.0 | E191: 10.29.22.0 | F191: 10.29.23.0 | G191: 10.29.24.0 | H191: 10.29.25.0 | I191: 10.29.26.0 | J191: 10.29.27.0 | K191: 10.29.28.0 | L191: =_xlfn.XLOOKUP(B191,Summary!B:B,Summary!G:G) -> 5 | O191: =N191&"-255" -> -255
A192: =_xlfn.XLOOKUP(B192,Summary!B:B,Summary!C:C,"") -> Antminer S21 | B192: C189 | C192: 10.21.255.189 | D192: 10.29.31.0 | E192: 10.29.32.0 | F192: 10.29.33.0 | G192: 10.29.34.0 | H192: 10.29.35.0 | I192: 10.29.36.0 | J192: 10.29.37.0 | K192: 10.29.38.0 | L192: =_xlfn.XLOOKUP(B192,Summary!B:B,Summary!G:G) -> 5 | O192: =N192&"-255" -> -255 | P192: Stock | Q192: 3800W
A193: =_xlfn.XLOOKUP(B193,Summary!B:B,Summary!C:C,"") -> Antminer S21 | B193: C190 | C193: 10.21.255.190 | D193: 10.29.41.0 | E193: 10.29.42.0 | F193: 10.29.43.0 | G193: 10.29.44.0 | H193: 10.29.45.0 | I193: 10.29.46.0 | J193: 10.29.47.0 | K193: 10.29.48.0 | L193: =_xlfn.XLOOKUP(B193,Summary!B:B,Summary!G:G) -> 5 | O193: =N193&"-255" -> -255 | P193: Stock | Q193: 3800W
A194: =_xlfn.XLOOKUP(B194,Summary!B:B,Summary!C:C,"") -> Antminer S21 | B194: C191 | C194: 10.21.255.191 | D194: 10.29.51.0 | E194: 10.29.52.0 | F194: 10.29.53.0 | G194: 10.29.54.0 | H194: 10.29.55.0 | I194: 10.29.56.0 | J194: 10.29.57.0 | K194: 10.29.58.0 | L194: =_xlfn.XLOOKUP(B194,Summary!B:B,Summary!G:G) -> 5 | O194: =N194&"-255" -> -255 | P194: Stock | Q194: 3800W
A195: =_xlfn.XLOOKUP(B195,Summary!B:B,Summary!C:C,"") -> Antminer S21 | B195: C192 | C195: 10.21.255.192 | D195: 10.29.61.0 | E195: 10.29.62.0 | F195: 10.29.63.0 | G195: 10.29.64.0 | H195: 10.29.65.0 | I195: 10.29.66.0 | J195: 10.29.67.0 | K195: 10.29.68.0 | L195: =_xlfn.XLOOKUP(B195,Summary!B:B,Summary!G:G) -> 5 | O195: =N195&"-255" -> -255 | P195: Stock | Q195: 3800W
A196: =_xlfn.XLOOKUP(B196,Summary!B:B,Summary!C:C,"") -> Antminer S21 | B196: C193 | C196: 10.21.255.193 | D196: 10.29.71.0 | E196: 10.29.72.0 | F196: 10.29.73.0 | G196: 10.29.74.0 | H196: 10.29.75.0 | I196: 10.29.76.0 | J196: 10.29.77.0 | K196: 10.29.78.0 | L196: =_xlfn.XLOOKUP(B196,Summary!B:B,Summary!G:G) -> 5 | O196: =N196&"-255" -> -255 | P196: Stock | Q196: 3800W
A197: =_xlfn.XLOOKUP(B197,Summary!B:B,Summary!C:C,"") -> Antminer S21 | B197: C194 | C197: 10.21.255.194 | D197: 10.29.81.0 | E197: 10.29.82.0 | F197: 10.29.83.0 | G197: 10.29.84.0 | H197: 10.29.85.0 | I197: 10.29.86.0 | J197: 10.29.87.0 | K197: 10.29.88.0 | L197: =_xlfn.XLOOKUP(B197,Summary!B:B,Summary!G:G) -> 5 | O197: =N197&"-255" -> -255 | P197: Stock | Q197: 3800W
A198: =_xlfn.XLOOKUP(B198,Summary!B:B,Summary!C:C,"") -> Antminer S21 | B198: C195 | C198: 10.21.255.195 | D198: 10.29.91.0 | E198: 10.29.92.0 | F198: 10.29.93.0 | G198: 10.29.94.0 | H198: 10.29.95.0 | I198: 10.29.96.0 | J198: 10.29.97.0 | K198: 10.29.98.0 | L198: =_xlfn.XLOOKUP(B198,Summary!B:B,Summary!G:G) -> 5 | O198: =N198&"-255" -> -255 | P198: Stock | Q198: 3800W
A199: =_xlfn.XLOOKUP(B199,Summary!B:B,Summary!C:C,"") -> Antminer S21 | B199: C196 | C199: 10.21.255.196 | D199: 10.29.101.0 | E199: 10.29.102.0 | F199: 10.29.103.0 | G199: 10.29.104.0 | H199: 10.29.105.0 | I199: 10.29.106.0 | J199: 10.29.107.0 | K199: 10.29.108.0 | L199: =_xlfn.XLOOKUP(B199,Summary!B:B,Summary!G:G) -> 5 | O199: =N199&"-255" -> -255 | P199: Stock | Q199: 3800W
A200: =_xlfn.XLOOKUP(B200,Summary!B:B,Summary!C:C,"") -> Antminer S21 | B200: C197 | C200: 10.21.255.197 | D200: 10.29.111.0 | E200: 10.29.112.0 | F200: 10.29.113.0 | G200: 10.29.114.0 | H200: 10.29.115.0 | I200: 10.29.116.0 | J200: 10.29.117.0 | K200: 10.29.118.0 | L200: =_xlfn.XLOOKUP(B200,Summary!B:B,Summary!G:G) -> 5 | O200: =N200&"-255" -> -255 | P200: Stock | Q200: 3800W
A201: =_xlfn.XLOOKUP(B201,Summary!B:B,Summary!C:C,"") -> Antminer S21 | B201: C198 | C201: 10.21.255.198 | D201: 10.29.121.0 | E201: 10.29.122.0 | F201: 10.29.123.0 | G201: 10.29.124.0 | H201: 10.29.125.0 | I201: 10.29.126.0 | J201: 10.29.127.0 | K201: 10.29.128.0 | L201: =_xlfn.XLOOKUP(B201,Summary!B:B,Summary!G:G) -> 5 | O201: =N201&"-255" -> -255 | P201: Stock | Q201: 3800W
A202: =_xlfn.XLOOKUP(B202,Summary!B:B,Summary!C:C,"") -> Antminer S21 | B202: C199 | C202: 10.21.255.199 | D202: 10.29.131.0 | E202: 10.29.132.0 | F202: 10.29.133.0 | G202: 10.29.134.0 | H202: 10.29.135.0 | I202: 10.29.136.0 | J202: 10.29.137.0 | K202: 10.29.138.0 | L202: =_xlfn.XLOOKUP(B202,Summary!B:B,Summary!G:G) -> 5 | O202: =N202&"-255" -> -255 | P202: Stock | Q202: 3800W
A203: =_xlfn.XLOOKUP(B203,Summary!B:B,Summary!C:C,"") -> Antminer S21 | B203: C200 | C203: 10.21.255.200 | D203: 10.29.141.0 | E203: 10.29.142.0 | F203: 10.29.143.0 | G203: 10.29.144.0 | H203: 10.29.145.0 | I203: 10.29.146.0 | J203: 10.29.147.0 | K203: 10.29.148.0 | L203: =_xlfn.XLOOKUP(B203,Summary!B:B,Summary!G:G) -> 5 | O203: =N203&"-255" -> -255 | P203: Stock | Q203: 3800W
... A209: =_xlfn.XLOOKUP(B209,Summary!B:B,Summary!C:C,"") -> Antminer S21 | B209: C206 | C209: 10.21.255.206 | D209: 10.29.201.0 | E209: 10.29.202.0 | F209: 10.29.203.0 | G209: 10.29.204.0 | H209: 10.29.205.0 | I209: 10.29.206.0 | J209: 10.29.207.0 | K209: 10.29.208.0 | L209: =_xlfn.XLOOKUP(B209,Summary!B:B,Summary!G:G) -> 5 | O209: =N209&"-255" -> -255 | P209: Stock | Q209: 3800W
A210: =_xlfn.XLOOKUP(B210,Summary!B:B,Summary!C:C,"") -> ** NOT USED ** | B210: C207 | C210: 10.21.255.207 | D210: 10.29.211.0 | E210: 10.29.212.0 | F210: 10.29.213.0 | G210: 10.29.214.0 | H210: 10.29.215.0 | I210: 10.29.216.0 | J210: 10.29.217.0 | K210: 10.29.218.0 | L210: =_xlfn.XLOOKUP(B210,Summary!B:B,Summary!G:G) -> 5 | O210: =N210&"-255" -> -255
A211: =_xlfn.XLOOKUP(B211,Summary!B:B,Summary!C:C,"") -> ** NOT USED ** | B211: C208 | C211: 10.21.255.208 | D211: 10.29.221.0 | E211: 10.29.222.0 | F211: 10.29.223.0 | G211: 10.29.224.0 | H211: 10.29.225.0 | I211: 10.29.226.0 | J211: 10.29.227.0 | K211: 10.29.228.0 | L211: =_xlfn.XLOOKUP(B211,Summary!B:B,Summary!G:G) -> 5 | O211: =N211&"-255" -> -255
A212: =_xlfn.XLOOKUP(B212,Summary!B:B,Summary!C:C,"") -> Antminer S21 | B212: C211 | C212: 10.21.255.211 | D212: 10.29.231.0 | E212: 10.29.232.0 | F212: 10.29.233.0 | G212: 10.29.234.0 | H212: 10.29.235.0 | I212: 10.29.236.0 | J212: 10.29.237.0 | K212: 10.29.238.0 | L212: =_xlfn.XLOOKUP(B212,Summary!B:B,Summary!G:G) -> 6 | O212: =N212&"-255" -> -255 | P212: 4400W | Q212: 3800W
A213: =_xlfn.XLOOKUP(B213,Summary!B:B,Summary!C:C,"") -> Antminer S21 | B213: C212 | C213: 10.21.255.212 | D213: 10.29.241.0 | E213: 10.29.242.0 | F213: 10.29.243.0 | G213: 10.29.244.0 | H213: 10.29.245.0 | I213: 10.29.246.0 | J213: 10.29.247.0 | K213: 10.29.248.0 | L213: =_xlfn.XLOOKUP(B213,Summary!B:B,Summary!G:G) -> 6 | O213: =N213&"-255" -> -255 | P213: 4400W | Q213: 3800W
...

Sheet eGauges
A1: XF # | B1: Containers | C1: SN | D1: Model | E1: IP Address | F1: MAC | G1: eGauge Name | H1: Default Username | I1: Default Password | J1: Custom Name | K1: LAN Username | L1: LAN Password | M1: Configured | N1: Notes
A2: XF000
A3: XF001 | B3: C000 / C001 | C3: 2201121400 | D3: EG4115 | E3: 10.21.10.7 | F3: f8:2f:5b:03:6d:c6 | G3: eGauge76695 | H3: owner | I3: rJv4F6h7 | J3: WH-XF001 | K3: mara | L3: marawh | M3: Yes
A4: XF002 | B4: C002 / C003 | C4: 2201121459 | D4: EG4115 | E4: 10.21.10.71 | F4: f8:2f:5b:03:6d:e2 | G4: eGauge76683 | H4: owner | I4: qYd5i9e4 | J4: WH-XF002 | K4: mara | L4: marawh | M4: Yes
A5: XF003 | B5: C004 / C005 | C5: 2502170489 | D5: EG4015 | E5: 10.21.10.199 | F5: f8:2f:5b:05:05:9a | G5: eGauge103568 | H5: owner | I5: Z9X4ZmAh | J5: WH-XF003 | N5: offline
A6: XF004 | B6: C006 / C007 | C6: 2502170311 | D6: EG4015 | E6: 10.21.60.20 | F6: f8:2f:5b:05:07:32 | G6: eGauge103569 | H6: owner | I6: d7bTpU8w | J6: WH-XF004 | K6: mara | L6: marawh | M6: Yes
A7: XF005 | B7: C008 / C009 | C7: 2502170031 | D7: EG4015 | E7: 10.21.80.20 | F7: f8:2f:5b:05:06:02 | G7: eGauge103574 | H7: owner | I7: y6h3V8iC | J7: WH-XF005 | K7: mara | L7: marawh | M7: Yes
A8: XF006 | B8: C010 / C011 | C8: 2310230190 | D8: EG4015 | E8: 10.21.100.20 | F8: f8:2f:5b:04:d7:3e | G8: eGauge103614 | H8: owner | I8: 2nC2S8g4 | J8: WH-XF006 | K8: mara | L8: marawh | M8: Yes
A9: XF007 | B9: C012 / C013 | C9: 2502170309 | D9: EG4015 | E9: 10.21.120.20 | F9: f8:2f:5b:05:07:2a | G9: eGauge103565 | H9: owner | I9: zGs8GqK8 | J9: WH-XF007 | K9: mara | L9: marawh | M9: Yes
A10: XF008 | B10: C014 / C015 | C10: 2201121018 | D10: EG4115 | E10: 10.10.2.197 | F10: f8:2f:5b:03:6e:36 | G10: eGauge76658 | H10: owner | I10: dG8yN5f4 | J10: WH-XF008 | N10: offline
A11: XF009 | B11: C016 / C017 | C11: 2201121466 | D11: EG4115 | E11: 10.22.40.20 | F11: f8:2f:5b:03:6e:3a | G11: eGauge76649 | H11: owner | I11: Bw4Tk3T4 | J11: WH-XF009 | K11: mara | L11: marawh | M11: Partial | N11: CT Sensor is reading 353KW
A12: XF010 | B12: C018 / C019 | C12: 2502170499 | D12: EG4015 | E12: 10.22.60.20 | F12: f8:2f:5b:05:05:c2 | G12: eGauge103560 | H12: owner | I12: 9Gj3Es8m | J12: WH-XF010 | K12: mara | L12: marawh | M12: Yes
A13: XF011 | B13: C020 / C021 | C13: 2502170192 | D13: EG4015 | E13: 10.22.80.20 | F13: f8:2f:5b:05:06:e6 | G13: eGauge103561 | H13: owner | I13: h9Jo9n3B | J13: WH-XF011 | K13: mara | L13: marawh | M13: Yes
A14: XF012 | B14: C022 / C023 | C14: 2502170194 | D14: EG4015 | E14: 10.22.100.20 | F14: f8:2f:5b:05:08:ee | G14: eGauge103567 | H14: owner | I14: 5s5vR7v8 | J14: WH-XF012 | K14: mara | L14: marawh | M14: Yes
A15: XF013 | B15: C024 / C025 | C15: 2502170206 | D15: EG4015 | E15: 10.22.120.20 | F15: f8:2f:5b:05:07:0e | G15: eGauge103566 | H15: owner | I15: s9J7N2C9 | J15: WH-XF013 | K15: mara | L15: marawh | M15: Yes
A16: XF014 | B16: C026 / C027 | C16: 2502170207 | D16: EG4015 | E16: 10.22.140.20 | F16: f8:2f:5b:05:07:12 | G16: eGauge103585 | H16: owner | I16: N2VoJuZj | J16: WH-XF014 | K16: mara | L16: marawh | M16: Yes
A17: XF015 | B17: C028 / C029 | C17: 2201121458 | D17: EG4115 | E17: 10.23.10.20 | F17: f8:2f:5b:03:62:2e | G17: eGauge76639 | H17: owner | I17: 2aL7X6pU | J17: WH-XF015 | K17: mara | L17: marawh | M17: Yes
A18: XF016 | B18: C030 / C031 | C18: 2201121314 | D18: EG4115 | E18: 10.23.30.20 | F18: f8:2f:5b:03:6d:6e | G18: eGauge76725 | H18: owner | I18: J4Cu2h2Y | J18: WH-XF016 | K18: mara | L18: marawh | M18: Yes | N18: CT Sensor reading 629KW
A19: XF017 | B19: C032 / C033 | C19: 2502170226 | D19: EG4015 | E19: 10.23.50.20 | F19: f8:2f:5b:05:07:ea | G19: eGauge103577 | H19: owner | I19: 4M8UhU3w | J19: WH-XF017 | K19: mara | L19: marawh | M19: Yes
A20: XF018 | B20: C034 / C035 | C20: 2502170408 | D20: EG4015 | E20: 10.23.70.20 | F20: f8:2f:5b:05:07:46 | G20: eGauge103564 | H20: owner | I20: Ge5J8ZaZ | J20: WH-XF018 | K20: mara | L20: marawh | M20: Yes
A21: XF019 | B21: C036 / C037 | C21: 2502170219 | D21: EG4015 | E21: 10.23.90.20 | F21: f8:2f:5b:05:08:e2 | G21: eGauge103573 | H21: owner | I21: 8Rd7Jv6J | J21: WH-XF019 | K21: mara | L21: marawh | M21: Yes
A22: XF020 | B22: C038 / C039 | C22: 2405070570 | D22: EG4015 | E22: 10.23.110.20 | F22: f8:2f:5b:04:db:8e | G22: eGauge101647 | H22: owner | I22: KfFf3jDb | J22: WH-XF020 | K22: mara | L22: marawh | M22: Yes
A23: XF021 | B23: C040 / C041 | C23: 2502170472 | D23: EG4015 | E23: 10.23.130.21 | F23: f8:2f:5b:05:05:86 | G23: eGauge103571 | H23: owner | I23: H2jMc8Tx | J23: WH-XF021 | K23: mara | L23: marawh | M23: Yes
A24: XF022 | B24: C042 / C043 | C24: 2201121500 | D24: EG4115 | E24: 10.24.20.20 | F24: f8:2f:5b:03:6d:ee | G24: eGauge76707 | H24: owner | I24: 3iR9F6e7 | J24: WH-XF022 | K24: mara | L24: marawh | M24: Yes | N24: CT Sensor reading 618KW
A25: XF023 | B25: C044 / C045 | C25: 2201121399 | D25: EG4115 | E25: 10.24.30.20 | F25: f8:2f:5b:03:6d:d2 | G25: eGauge76715 | H25: owner | I25: 7NhH4aLa | J25: WH-XF023 | K25: mara | L25: marawh | M25: Yes
A26: XF024 | B26: C046 / C047 | C26: 2502170246 | D26: EG4015 | E26: 10.24.60.20 | F26: f8:2f:5b:05:07:f2 | G26: eGauge103583 | H26: owner | I26: 5Y9kU6W4 | J26: WH-XF024 | K26: mara | L26: marawh | M26: Yes
A27: XF025 | B27: C049 | C27: 2502170041 | D27: EG4015 | E27: 10.24.80.20 | F27: f8:2f:5b:05:06:1a | G27: eGauge103575 | H27: owner | I27: aJ9s5Bc4 | J27: WH-XF025 | K27: mara | L27: marawh | M27: Yes
A28: XF026 | B28: C050 / C051 | C28: 2502170312 | D28: EG4015 | E28: 10.24.100.20 | F28: f8:2f:5b:05:07:36 | G28: eGauge103563 | H28: owner | I28: WeU6y9Wx | J28: WH-XF026 | K28: mara | L28: marawh | M28: Yes
A29: XF027 | B29: C052 / C053 | C29: 2502170443 | D29: EG4015 | E29: 10.24.120.20 | F29: f8:2f:5b:05:05:52 | G29: eGauge103581 | H29: owner | I29: 5m7VrG6M | J29: WH-XF027 | K29: mara | L29: marawh | M29: Yes
A30: XF028 | B30: C054 / C055 | C30: 2502170498 | D30: EG4015 | E30: 10.24.140.20 | F30: f8:2f:5b:05:05:be | G30: eGauge103076 | H30: owner | I30: 4YuUn3e9 | J30: WH-XF028 | K30: mara | L30: marawh | M30: Yes
A31: XF029 | B31: C056 / C057 | C31: 2502170196 | D31: EG4015 | E31: 10.21.140.20 | F31: f8:2f:5b:05:06:f6 | G31: eGauge103559 | H31: owner | I31: g2wShE8w | J31: WH-XF029 | N31: offline
A32: XF030 | B32: C058 / C059 | C32: 2502170191 | D32: EG4015 | E32: 10.21.160.20 | F32: f8:2f:5b:05:06:e2 | G32: eGauge103562 | H32: owner | I32: N6hFw4bF | J32: WH-XF030 | K32: mara | L32: marawh | M32: Yes
A33: XF031 | B33: C060 / C061 | C33: 2310230184 | D33: EG4015 | E33: 10.22.160.20 | F33: f8:2f:5b:04:d7:4e | G33: eGauge103616 | H33: owner | I33: X5F3X6Zc | J33: WH-XF031 | K33: mara | L33: marawh | M33: Yes
A34: XF032 | B34: C062 / C063 | C34: 2502170464 | D34: EG4015 | E34: 10.22.180.20 | F34: f8:2f:5b:05:05:66 | G34: eGauge103579 | H34: owner | I34: C2f7Vu3b | J34: WH-XF032 | K34: mara | L34: marawh | M34: Yes
A35: XF033 | B35: C064 / C065 | C35: 2502170310 | D35: EG4015 | E35: 10.23.150.20 | F35: f8:2f:5b:05:07:2e | G35: eGauge103570 | H35: owner | I35: TtC9Nw2h | J35: WH-XF033 | K35: mara | L35: marawh | M35: Yes
A36: XF034 | B36: C066 / C067 | C36: 2405070266 | D36: EG4015 | E36: 10.23.170.20 | F36: f8:2f:5b:04:ef:36 | G36: eGauge101609 | H36: owner | I36: a5w9H9Sv | J36: WH-XF034 | K36: mara | L36: marawh | M36: Yes
A37: XF035 | B37: C068 / C069 | C37: 2502170406 | D37: EG4015 | E37: 10.24.160.20 | F37: f8:2f:5b:05:07:3e | G37: eGauge103588 | H37: owner | I37: sM6gZv4E | J37: WH-XF035 | K37: mara | L37: marawh | M37: Yes
A38: XF036 | B38: C070 / C071 | C38: 2502170431 | D38: EG4015 | E38: 10.24.180.20 | F38: f8:2f:5b:05:08:42 | G38: eGauge103582 | H38: owner | I38: Du8N2Ng5 | J38: WH-XF036 | K38: mara | L38: marawh | M38: Yes
A39: XF037 | B39: C072 / C073 | C39: 2310230171 | D39: EG4015 | E39: 10.21.190.20 | F39: f8:2f:5b:04:d6:86 | G39: eGauge103612 | H39: owner | I39: Av3n9rLa | J39: WH-XF037 | K39: mara | L39: marawh | M39: Yes
A40: XF038 | B40: C074 / C075 | C40: 2502170193 | D40: EG4015 | E40: 10.21.200.20 | F40: f8:2f:5b:05:06:ea | G40: eGauge103584 | H40: owner | I40: eMhA2Vm5 | J40: WH-XF038 | K40: mara | L40: marawh | M40: Yes
A41: XF039 | B41: C076 / C077 | C41: 2405070672 | D41: EG4015 | E41: 10.22.200.20 | F41: f8:2f:5b:04:db:c2 | G41: eGauge101650 | H41: owner | I41: 5EvA6z7B | J41: WH-XF039 | K41: mara | L41: marawh | M41: Yes
A42: XF040 | B42: C078 / C079 | C42: 2405070257 | D42: EG4015 | E42: 10.22.210.20 | F42: f8:2f:5b:04:ef:12 | G42: eGauge101605 | H42: owner | I42: 9a7o7Bt4 | J42: WH-XF040 | K42: mara | L42: marawh | M42: Yes
A43: XF041 | B43: C080 / C081 | C43: 2502170190 | D43: EG4015 | E43: 10.22.240.20 | F43: f8:2f:5b:05:06:de | G43: eGauge103596 | H43: owner | I43: 4d4Hk5Gi | J43: WH-XF041 | K43: mara | L43: marawh | M43: Yes
... A48: XF046 | B48: C090 / C091 | C48: 2201121405 | D48: EG4115 | E48: 10.25.10.21 | F48: f8:2f:5b:03:6d:ea | G48: eGauge76692 | H48: owner | I48: Vk7J8F8Y | J48: WH-XF046 | K48: mara | L48: marawh | M48: Yes
A49: XF047 | B49: C092 / C093 | C49: 2205180079 | D49: EG4115 | E49: 10.25.40.21 | F49: f8:2f:5b:03:84:06 | G49: eGauge76763 | H49: owner | I49: bX2As8rR | J49: WH-XF047 | K49: mara | L49: marawh | M49: Yes | N49: CT Sensor reading 585KW
A50: XF048 | B50: C094 / C095 | C50: 2201121175 | D50: EG4115 | E50: 10.25.50.20 | F50: f8:2f:5b:03:6c:f6 | G50: eGauge76722 | H50: owner | I50: u5pK2A8U | J50: WH-XF048 | K50: mara | L50: marawh | M50: Yes
A51: XF049 | B51: C096 / C097 | C51: 2205180078 | D51: EG4115 | E51: 10.25.80.21 | F51: f8:2f:5b:03:84:10 | G51: eGauge76773 | H51: owner | I51: P2CfAu5d | J51: WH-XF049 | K51: mara | L51: marawh | M51: Yes
A52: XF050 | B52: C098 / C099 | C52: 2205180124 | D52: EG4115 | E52: 10.25.90.21 | F52: f8:2f:5b:03:84:3e | G52: eGauge76765 | H52: owner | I52: B2E6Ey9D | J52: WH-XF050 | K52: mara | L52: marawh | M52: Yes
A53: XF051 | B53: C100 / C101 | C53: 2201121417 | D53: EG4115 | E53: 10.25.120.21 | F53: f8:2f:5b:03:69:1a | G53: eGauge76666 | H53: owner | I53: gY8E9TcH | J53: WH-XF051 | K53: mara | L53: marawh | M53: Yes
A54: XF052 | B54: C102 / C103 | C54: 2201121425 | D54: EG4115 | E54: 10.25.130.20 | F54: f8:2f:5b:03:69:0a | G54: eGauge76726 | H54: owner | I54: wVfUo2d7 | J54: WH-XF052 | K54: mara | L54: marawh | M54: Yes
A55: XF053 | B55: C104 / C105 | C55: 2102150417 | D55: EG4115 | E55: 10.25.160.21 | F55: f8:2f:5b:02:fe:ee | G55: eGauge67288 | H55: owner | I55: L5Ka9SzJ | J55: WH-XF053 | K55: mara | L55: marawh | M55: Yes
A56: XF054 | B56: C106 / C107 | C56: 2201121319 | D56: EG4115 | E56: 10.25.170.22 | F56: f8:2f:5b:03:6d:36 | G56: eGauge76698 | H56: owner | I56: 4C6P5T6S | J56: WH-XF054 | K56: mara | L56: marawh | M56: Yes
A57: XF055 | B57: C108 / C109 | C57: 2201121182 | D57: EG4115 | E57: 10.25.200.20 | F57: f8:2f:5b:03:6d:2a | G57: eGauge76693 | H57: owner | I57: eWh6N9w4 | J57: WH-XF055 | K57: mara | L57: marawh | M57: Yes
A58: XF056 | B58: C110 / C111 | C58: 2201121179 | D58: EG4115 | E58: 10.25.210.21 | F58: f8:2f:5b:03:6d:2e | G58: eGauge76690 | H58: owner | I58: o5d6iHx9 | J58: WH-XF056 | K58: mara | L58: marawh | M58: Yes
A59: XF057 | B59: C112 / C113 | C59: 2201121321 | D59: EG4115 | E59: 10.25.240.20 | F59: f8:2f:5b:03:6d:56 | G59: eGauge76689 | H59: owner | I59: k9MaLj3A | J59: WH-XF057 | K59: mara | L59: marawh | M59: Yes
A60: XF058 | B60: C114 / C115 | C60: 2102150387 | D60: EG4115 | E60: 10.26.10.20 | F60: f8:2f:5b:02:fe:f2 | G60: eGauge67287 | H60: owner | I60: 7vWm2R7G | J60: WH-XF058 | K60: mara | L60: marawh | M60: Yes
A61: XF059 | B61: C116 / C117 | C61: 2201121358 | D61: EG4115 | E61: 10.26.40.20 | F61: f8:2f:5b:03:5f:40 | G61: eGauge76637 | H61: owner | I61: h8sAr3k6 | J61: WH-XF059 | K61: mara | L61: marawh | M61: Yes
... A87: XF085 | B87: C168 / C169 | C87: 2502170127 | D87: EG4015 | E87: 10.28.80.20 | F87: f8:2f:5b:05:06:d2 | G87: eGauge103594 | H87: owner | I87: e3d5tRb9 | J87: WH-XF085 | K87: mara | L87: marawh | M87: Yes
A88: XF086 | B88: C170 / C171 | C88: 2310230149 | D88: EG4015 | E88: 10.28.90.20 | F88: f8:2f:5b:04:d7:26 | G88: eGauge103606 | H88: owner | I88: 9Bi9S8wV | J88: WH-XF086 | K88: mara | L88: marawh | M88: Partial | N88: CT Sensor reading 819KW
A89: XF087 | B89: C172 / C173 | C89: 2502170128 | D89: EG4015 | E89: 10.28.120.21 | F89: f8:2f:5b:05:06:d6 | G89: eGauge103600 | H89: owner | I89: k8h3tD9r | J89: WH-XF087 | K89: mara | L89: marawh | M89: Yes
A90: XF088 | B90: C174 / C175 | C90: 2502170051 | D90: EG4015 | E90: 10.28.130.20 | F90: f8:2f:5b:05:06:42 | G90: eGauge103590 | H90: owner | I90: rEv3M9V5 | J90: WH-XF088 | K90: mara | L90: marawh | M90: Yes
A91: XF089 | B91: C176 / C177 | C91: 2502170126 | D91: EG4015 | E91: 10.28.160.21 | F91: f8:2f:5b:05:06:ce | G91: eGauge103597 | H91: owner | I91: 3Lh3bKi8 | J91: WH-XF089 | K91: mara | L91: marawh | M91: Yes
A92: XF090 | B92: C178 / C179 | C92: 2405070333 | D92: EG4015 | E92: 10.28.170.20 | F92: f8:2f:5b:04:f0:06 | G92: eGauge101616 | H92: owner | I92: UeA2gUkN | J92: WH-XF090 | K92: mara | L92: marawh | M92: Yes
A93: XF091 | B93: C180 / C181 | C93: 2310230192 | D93: EG4015 | E93: 10.28.200.21 | F93: f8:2f:5b:04:d6:e6 | G93: eGauge103607 | H93: owner | I93: iGjB5wU6 | J93: WH-XF091 | K93: mara | L93: marawh | M93: Yes
A94: XF092 | B94: C182 / C183 | C94: 2405070438 | D94: EG4015 | E94: 10.28.210.20 | F94: f8:2f:5b:04:ef:d6 | G94: eGauge101625 | H94: owner | I94: 2Dg7Mg2V | J94: WH-XF092 | K94: mara | L94: marawh | M94: Yes
A95: XF093 | B95: C184 / C185 | C95: 2405070444 | D95: EG4015 | E95: 10.28.240.22 | F95: f8:2f:5b:04:ef:ee | G95: eGauge101623 | H95: owner | I95: RuLgB5Mp | J95: WH-XF093 | K95: mara | L95: marawh | M95: Yes
A96: XF094 | H96: owner | J96: Not in Use
A97: XF095 | B97: C188 | C97: 2205180066 | D97: EG4115 | E97: 10.31.0.151 | F97: f8:2f:5b:03:82:62 | G97: eGauge76749 | H97: owner | I97: MpEz6K3Y | J97: WH-XF095 | K97: mara | L97: marawh | M97: Yes
A98: XF096 | B98: C189 / C190 | C98: 2502170125 | D98: EG4015 | E98: 10.29.40.21 | F98: f8:2f:5b:05:06:ca | G98: eGauge103598 | H98: owner | I98: ZkX4fDbB | J98: WH-XF096 | K98: mara | L98: marawh | M98: Yes
A99: XF097 | B99: C191 / C192 | C99: 2502170477 | D99: EG4015 | E99: 10.29.50.21 | F99: f8:2f:5b:05:05:8a | G99: eGauge103592 | H99: owner | I99: n9q3iJ2L | J99: WH-XF097 | K99: mara | L99: marawh | M99: Yes
A100: XF098 | B100: C193 / C194 | C100: 2405070155 | D100: EG4015 | E100: 10.29.80.21 | F100: f8:2f:5b:04:ef:fe | G100: eGauge101618 | H100: owner | I100: 6X7gW7p6 | J100: WH-XF098 | K100: mara | L100: marawh | M100: Yes
A101: XF099 | B101: C195 / C196 | C101: 2405070684 | D101: EG4015 | E101: 10.29.90.22 | F101: f8:2f:5b:04:db:e2 | G101: eGauge101644 | H101: owner | I101: Ci6F5dV4m | J101: WH-XF099 | K101: mara | L101: marawh | M101: Yes
A102: XF100 | B102: C197 / C198 | C102: 2310230170 | D102: EG4015 | E102: 10.29.120.21 | F102: f8:2f:5b:04:d7:a6 | G102: eGauge103601 | H102: owner | I102: j9t6y4H9 | J102: WH-XF100 | K102: mara | L102: marawh | M102: Yes
A103: XF101 | B103: C199 / C200 | C103: 2502170405 | D103: EG4015 | E103: 10.29.130.21 | F103: f8:2f:5b:05:07:3a | G103: eGauge103595 | H103: owner | I103: z9V5c3Aa | J103: WH-XF101 | K103: mara | L103: marawh | M103: Yes
A104: XF102 | B104: C201 / C202 | C104: 2502170204 | D104: EG4015 | E104: 10.29.160.21 | F104: f8:2f:5b:05:07:06 | G104: eGauge103599 | H104: owner | I104: 5V7n3b2H | J104: WH-XF102 | K104: mara | L104: marawh | M104: Yes
A105: XF103 | B105: C203 / C204 | C105: 2502170205 | D105: EG4015 | E105: 10.29.170.21 | F105: f8:2f:5b:05:07:0a | G105: eGauge103593 | H105: owner | I105: yBdG6C9t | J105: WH-XF103 | K105: mara | L105: marawh | M105: Yes
A106: XF104 | B106: C205 / C206 | C106: 2405070439 | D106: EG4015 | E106: 10.29.200.20 | F106: f8:2f:5b:04:ef:da | G106: eGauge101624 | H106: owner | I106: HnF3t3sR | J106: WH-XF104 | K106: mara | L106: marawh | M106: Yes
A107: XF105 | H107: owner | J107: Not in Use
A108: XF106 | B108: C209 | C108: 2205180292 | D108: EG4115 | E108: 10.31.4.147 | F108: f8:2f:5b:03:84:2a | G108: eGauge76770 | H108: owner | I108: cSoAdGa8 | J108: WH-XF106 | K108: mara | L108: marawh | M108: Yes
A109: XF107 | B109: C210 | C109: 2102150548 | D109: EG4115 | E109: 10.31.8.11 | F109: f8:2f:5b:02:fe:12 | G109: eGauge67281 | H109: owner | I109: p3yRgPn2 | J109: WH-XF107 | K109: mara | L109: marawh | M109: Yes
A110: XF108 | B110: C211 / C212 | C110: 2310230140 | D110: EG4015 | E110: 10.29.240.20 | F110: f8:2f:5b:04:d7:62 | G110: eGauge103615 | H110: owner | I110: 3L4M6A5c | J110: WH-XF108 | K110: mara | L110: marawh | M110: Yes | N110: CT sensor reading 703KW
A111: XF109 | B111: C213 / C214 | C111: 2310230114 | D111: EG4015 | E111: 10.30.10.20 | F111: f8:2f:5b:04:d6:6a | G111: eGuage103608 | H111: owner | I111: s3j4w9d3 | J111: WH-XF109 | K111: mara | L111: marawh | M111: Yes
A112: XF110 | B112: C215 / C216 | C112: 2502170045 | D112: EG4015 | E112: 10.30.40.20 | F112: f8:2f:5b:05:06:2a | G112: eGauge103591 | H112: owner | I112: aS2g4VkD | J112: WH-XF110 | K112: mara | L112: marawh | M112: Yes
A113: XF111 | B113: C217 / C218 | C113: 2310230199 | D113: EG4015 | E113: 10.30.50.20 | F113: f8:2f:5b:04:d6:ce | G113: eGauge103602 | H113: owner | I113: C4E3WpPt | J113: WH-XF111 | K113: mara | L113: marawh | M113: Yes
A114: XF112 | B114: C219 / C220 | C114: 2405070255 | D114: EG4015 | E114: 10.30.80.20 | F114: f8:2f:5b:04:ef:0a | G114: eGauge101606 | H114: owner | I114: C3g9t2B4 | J114: WH-XF112 | K114: mara | L114: marawh | M114: Yes
A115: XF113 | B115: C221 / C222 | C115: 2502170201 | D115: EG4015 | E115: 10.30.90.20 | F115: f8:2f:5b:05:06:fa | G115: eGauge103578 | H115: owner | I115: r2M6q5Lr | J115: WH-XF113 | K115: mara | L115: marawh | M115: Yes
A116: XF114 | B116: C223 | C116: 2405070755 | D116: EG4015 | E116: 10.31.12.150 | F116: f8:2f:5b:03:6e:2e | G116: eGauge101637 | H116: owner | I116: 9s3gYo2J | J116: WH-XF114 | K116: mara | L116: marawh | M116: Yes
A117: XF115 | B117: C224 | C117: 2102150574 | D117: EG4115 | E117: 10.31.16.149 | F117: f8:2f:5b:03:0a:ea | G117: eGauge67278 | H117: owner | I117: wN8C8o3G | J117: WH-XF115 | K117: mara | L117: marawh | M117: Yes
A118: XF116 | B118: C225 | C118: 2205180122 | D118: EG4115 | E118: 10.10.2 | F118: f8:2f:5b:03:84:7a | G118: eGauge76766 | H118: owner | I118: 5Y4B2s9E | J118: WH-XF116 | N118: no power
A119: XF117 | B119: C226 | C119: 2201121311 | D119: EG4115 | E119: 10.31.24.147 | F119: f8:2f:5b:03:6d:26 | G119: eGauge76704 | H119: owner | I119: AjJk7v6c | J119: WH-XF117 | K119: mara | L119: marawh | M119: Yes
A120: XF118 | B120: C227 / C228 | C120: 2405061056 | D120: EG4015 | E120: 10.30.120.20 | F120: f8:2f:5b:04:dd:f6 | G120: eGauge101642 | H120: owner | I120: W4kKdB5P | J120: WH-XF118 | K120: mara | L120: marawh | M120: Yes
A121: XF119 | B121: C229 / C230 | C121: 2201121318 | D121: EG4115 | E121: 10.30.130.20 | F121: f8:2f:5b:03:6d:5e | G121: eGauge76720 | H121: owner | I121: C4iN9P7U | J121: WH-XF119 | K121: mara | L121: marawh | M121: Yes
A122: XF120 | B122: C231 / C232 | C122: 2310230175 | D122: EG4015 | E122: 10.30.160.20 | F122: f8:2f:5v:04:d7:16 | G122: eGauge103603 | H122: owner | I122: M2c2Kg3C | J122: WH-XF120 | K122: mara | L122: marawh | M122: Yes
A123: XF121 | B123: C233 / C234 | C123: 2405070261 | D123: EG4015 | E123: 10.30.170.20 | F123: f8:2f:5b:04:ef:22 | G123: eGauge101611 | H123: owner | I123: RdSuBeR7 | J123: WH-XF121 | K123: mara | L123: marawh | M123: Yes
A124: XF122 | B124: C235 / C236 | C124: 2310230162 | D124: EG4015 | E124: 10.30.200.20 | F124: f8:2f:5b:04:d6:d6 | G124: eGauge103605 | H124: owner | I124: LcY6i6vT | J124: WH-XF122 | K124: mara | L124: marawh | M124: Yes
A125: XF123 | B125: C237 / C238 | C125: 2502170212 | D125: EG4015 | E125: 10.30.210.20 | F125: f8:2f:5b:05:07:22 | G125: eGauge103586 | H125: owner | I125: e6W6u6W7 | J125: WH-XF123 | K125: mara | L125: marawh | M125: Yes
A126: XF124 | B126: C239 | C126: 2201121312 | D126: EG4115 | E126: 10.31.28.155 | F126: f8:2f:5b:03:6d:12 | G126: eGauge76703 | H126: owner | I126: hN7T7s6n | J126: WH-XF124 | K126: mara | L126: marawh | M126: Yes
A127: XF125 | B127: C240 | C127: 2205180092 | D127: EG4115 | E127: 10.31.32.10 | F127: f8:2f:5b:03:84:5a | G127: eGauge76774 | H127: owner | I127: 9zB3a9q7 | J127: WH-XF125 | K127: mara | L127: marawh | M127: Yes
A128: XF126 | B128: C241 | C128: 2201121419 | D128: EG4115 | E128: 10.31.36.148 | F128: f8:2f:5b:03:69:06 | G128: eGauge76732 | H128: owner | I128: a4nL3D5r | J128: WH-XF126 | K128: mara | L128: marawh | M128: Yes
A129: XF127 | B129: C242 | C129: 2201121495 | D129: EG4115 | E129: 10.31.40.151 | F129: f8:2f:5b:03:6e:42 | G129: eGauge76638 | H129: owner | I129: 7T2Um9dC | J129: WH-XF127 | K129: mara | L129: marawh | M129: Yes
...

Sheet IP Ranges - Air (OLD)
A1: VLAN ID | B1: Purpose | C1: Containers | D1: Netblock | E1: Gateway | F1: Size | G1: DHCP Range | H1: V1 | I1: V2 | J1: V3 | M1: IP Ranges
A2: 1 | B2: CN Internal | C2: SCADA | D2: 10.10.0.0 | E2: 10.10.0.254 | F2: /24 | G2: .200-.225
A3: =A2+1 -> 2 | B3: Antminer | C3: C246 | D3: 10.10.100.0 | E3: ="10.10."&A3&".254" -> 10.10.2.254 | F3: /24 | G3: .1-.250 | I3: C246 | M3: 10.10.100.0-254
A4: =A3+1 -> 3 | B4: Antminer | C4: C246 | D4: 10.10.101.0 | E4: ="10.10."&A4&".254" -> 10.10.3.254 | F4: /24 | G4: .1-.250 | J4: C246 | M4: 10.10.101.0-254
A5: =A4+1 -> 4 | B5: Whatsminer | C5: C252 | D5: 10.10.104.0 | E5: ="10.10."&A5&".254" -> 10.10.4.254 | F5: /24 | G5: .1-.250 | H5: C252 | M5: 10.10.104.0-254
A6: =A5+1 -> 5 | B6: Whatsminer | C6: C252 | D6: 10.10.105.0 | E6: ="10.10."&A6&".254" -> 10.10.5.254 | F6: /24 | G6: .1-.250 | I6: C252 | M6: 10.10.105.0-254
A7: =A6+1 -> 6 | B7: Whatsminer | C7: C252 | D7: 10.10.106.0 | E7: ="10.10."&A7&".254" -> 10.10.6.254 | F7: /24 | G7: .1-.250 | J7: C252 | M7: 10.10.106.0-254
A8: =A7+1 -> 7 | B8: Whatsminer | C8: C260 | D8: 10.10.111.0 | E8: ="10.10."&A8&".254" -> 10.10.7.254 | F8: /24 | G8: .1-.250 | H8: C260 | M8: 10.10.111.0-254
A9: =A8+1 -> 8 | B9: Whatsminer | C9: C263 | D9: 10.10.112.0 | E9: ="10.10."&A9&".254" -> 10.10.8.254 | F9: /24 | G9: .1-.250 | I9: C263 | M9: 10.10.112.0-254
A10: 9 | D10: 10.10.9.0 | E10: 10.10.9.254 | F10: /24 | G10: .1-.250
A11: 10 | D11: 10.10.10.0 | E11: ="10.10."&A11&".254" -> 10.10.10.254 | F11: /24 | G11: .1-.250
A12: =A11+1 -> 11 | D12: 10.10.11.0 | E12: ="10.10."&A12&".254" -> 10.10.11.254 | F12: /24 | G12: .1-.250
A13: =A12+1 -> 12 | D13: 10.10.12.0 | E13: ="10.10."&A13&".254" -> 10.10.12.254 | F13: /24 | G13: .1-.250
A14: =A13+1 -> 13 | D14: 10.10.13.0 | E14: ="10.10."&A14&".254" -> 10.10.13.254 | F14: /24 | G14: .1-.250
A15: =A14+1 -> 14 | D15: 10.10.14.0 | E15: ="10.10."&A15&".254" -> 10.10.14.254 | F15: /24 | G15: .1-.250
A16: =A15+1 -> 15 | D16: 10.10.15.0 | E16: ="10.10."&A16&".254" -> 10.10.15.254 | F16: /24 | G16: .1-.250
A17: =A16+1 -> 16 | D17: 10.10.16.0 | E17: ="10.10."&A17&".254" -> 10.10.16.254 | F17: /24 | G17: .1-.250
A18: =A17+1 -> 17 | D18: 10.10.17.0 | E18: ="10.10."&A18&".254" -> 10.10.17.254 | F18: /24 | G18: .1-.250
A19: =A18+1 -> 18 | D19: 10.10.18.0 | E19: ="10.10."&A19&".254" -> 10.10.18.254 | F19: /24 | G19: .1-.250
A20: =A19+1 -> 19 | D20: 10.10.19.0 | E20: ="10.10."&A20&".254" -> 10.10.19.254 | F20: /24 | G20: .1-.250
A21: =A20+1 -> 20 | D21: 10.10.20.0 | E21: ="10.10."&A21&".254" -> 10.10.20.254 | F21: /24 | G21: .1-.250
A22: =A21+1 -> 21 | D22: 10.10.21.0 | E22: ="10.10."&A22&".254" -> 10.10.21.254 | F22: /24 | G22: .1-.250
A23: =A22+1 -> 22 | D23: 10.10.22.0 | E23: ="10.10."&A23&".254" -> 10.10.22.254 | F23: /24 | G23: .1-.250
... A31: =A30+1 -> 30 | D31: 10.10.30.0 | E31: ="10.10."&A31&".254" -> 10.10.30.254 | F31: /24 | G31: .1-.250
A32: 255 | D32: 10.10.255.0 | E32: ="10.10."&A32&".254" -> 10.10.255.254 | F32: /24 | G32: .1-.250
A33: 256 | B33: No DHCP pool? | D33: 10.11.0.0 | E33: 10.11.0.254 | F33: /24 | G33: .1-.250
A34: 257 | D34: 10.11.1.0 | E34: ="10.11."&#REF!&".254" -> #REF! | F34: /24 | G34: .1-.250
A35: 258 | D35: 10.11.2.0 | E35: ="10.11."&#REF!&".254" -> #REF! | F35: /24 | G35: .1-.250
A36: 259 | D36: 10.11.3.0 | E36: ="10.11."&#REF!&".254" -> #REF! | F36: /24 | G36: .1-.250
A37: 260 | D37: 10.11.4.0 | E37: ="10.11."&#REF!&".254" -> #REF! | F37: /24 | G37: .1-.250
A38: 261 | D38: 10.11.5.0 | E38: ="10.11."&#REF!&".254" -> #REF! | F38: /24 | G38: .1-.250
A39: 262 | D39: 10.11.6.0 | E39: ="10.11."&#REF!&".254" -> #REF! | F39: /24 | G39: .1-.250
A40: 263 | D40: 10.11.7.0 | E40: ="10.11."&#REF!&".254" -> #REF! | F40: /24 | G40: .1-.250
A41: 264 | D41: 10.11.8.0 | E41: ="10.11."&#REF!&".254" -> #REF! | F41: /24 | G41: .1-.250
A42: 265 | D42: 10.11.9.0 | E42: ="10.11."&#REF!&".254" -> #REF! | F42: /24 | G42: .1-.250
A43: 266 | D43: 10.11.10.0 | E43: ="10.11."&#REF!&".254" -> #REF! | F43: /24 | G43: .1-.250
A44: 267 | D44: 10.11.11.0 | E44: ="10.11."&#REF!&".254" -> #REF! | F44: /24 | G44: .1-.250
A45: 268 | D45: 10.11.12.0 | E45: ="10.11."&#REF!&".254" -> #REF! | F45: /24 | G45: .1-.250
... A71: 294 | D71: 10.11.38.0 | E71: ="10.11."&#REF!&".254" -> #REF! | F71: /24 | G71: .1-.250
A72: =A71+1 -> 295 | B72: Antminer | C72: C225 | D72: 10.10.113.0 | E72: ="10.10."&A72&".254" -> 10.10.295.254 | F72: /24 | G72: .1-.250 | H72: C225 | M72: =D72&"-254" -> 10.10.113.0-254
A73: =A72+1 -> 296 | B73: Antminer | C73: C225 | D73: 10.10.114.0 | E73: ="10.10."&A73&".254" -> 10.10.296.254 | F73: /24 | G73: .1-.250 | I73: C225 | M73: =D73&"-254" -> 10.10.114.0-254
A74: =A73+1 -> 297 | B74: Antminer | C74: C225 | D74: 10.10.115.0 | E74: ="10.10."&A74&".254" -> 10.10.297.254 | F74: /24 | G74: .1-.250 | J74: C225 | M74: =D74&"-254" -> 10.10.115.0-254
A75: 296 | D75: 10.11.40.0 | E75: ="10.11."&#REF!&".254" -> #REF! | F75: /24 | G75: .1-.250
A76: =A75+1 -> 297 | B76: Whatsminer | C76: C264 | D76: 10.10.117.0 | E76: ="10.10."&A76&".254" -> 10.10.297.254 | F76: /24 | G76: .1-.250 | J76: C264 | M76: =D76&"-254" -> 10.10.117.0-254
A77: 297 | D77: 10.11.41.0 | E77: ="10.11."&#REF!&".254" -> #REF! | F77: /24 | G77: .1-.250
A78: =A77+1 -> 298 | B78: Whatsminer | C78: C267 | D78: 10.10.128.0 | E78: ="10.10."&A78&".254" -> 10.10.298.254 | F78: /24 | G78: .1-.250 | H78: C267 | M78: =D78&"-254" -> 10.10.128.0-254
A79: 298 | D79: 10.11.42.0 | E79: ="10.11."&#REF!&".254" -> #REF! | F79: /24 | G79: .1-.250
A80: =A79+1 -> 299 | B80: Whatsminer | C80: C267 | D80: 10.10.129.0 | E80: ="10.10."&A80&".254" -> 10.10.299.254 | F80: /24 | G80: .1-.250 | I80: C267 | M80: =D80&"-254" -> 10.10.129.0-254
A81: 299 | D81: 10.11.43.0 | E81: ="10.11."&#REF!&".254" -> #REF! | F81: /24 | G81: .1-.250
A82: =A81+1 -> 300 | B82: Whatsminer | C82: C267 | D82: 10.10.130.0 | E82: ="10.10."&A82&".254" -> 10.10.300.254 | F82: /24 | G82: .1-.250 | J82: C267 | M82: =D82&"-254" -> 10.10.130.0-254
A83: 300 | D83: 10.11.44.0 | E83: ="10.11."&#REF!&".254" -> #REF! | F83: /24 | G83: .1-.250
A84: =A83+1 -> 301 | B84: Whatsminer | C84: C259 | D84: 10.10.131.0 | E84: ="10.10."&A84&".254" -> 10.10.301.254 | F84: /24 | G84: .1-.250 | H84: C259 | M84: =D84&"-254" -> 10.10.131.0-254
A85: 301 | D85: 10.11.45.0 | E85: ="10.11."&#REF!&".254" -> #REF! | F85: /24 | G85: .1-.250
A86: =A85+1 -> 302 | B86: Whatsminer | C86: C259 | D86: 10.10.132.0 | E86: ="10.10."&A86&".254" -> 10.10.302.254 | F86: /24 | G86: .1-.250 | I86: C259 | M86: =D86&"-254" -> 10.10.132.0-254
A87: 302 | D87: 10.11.46.0 | E87: ="10.11."&#REF!&".254" -> #REF! | F87: /24 | G87: .1-.250
A88: =A87+1 -> 303 | B88: Whatsminer | C88: C259 / C262 | D88: 10.10.133.0 | E88: ="10.10."&A88&".254" -> 10.10.303.254 | F88: /24 | G88: .1-.250 | H88: C262 | J88: C259 | M88: =D88&"-254" -> 10.10.133.0-254
A89: 303 | D89: 10.11.47.0 | E89: ="10.11."&#REF!&".254" -> #REF! | F89: /24 | G89: .1-.250
A90: =A89+1 -> 304 | B90: Whatsminer | C90: C262 | D90: 10.10.134.0 | E90: ="10.10."&A90&".254" -> 10.10.304.254 | F90: /24 | G90: .1-.250 | I90: C262 | M90: =D90&"-254" -> 10.10.134.0-254
A91: 304 | D91: 10.11.48.0 | E91: ="10.11."&#REF!&".254" -> #REF! | F91: /24 | G91: .1-.250
A92: =A91+1 -> 305 | B92: Whatsminer | C92: C262 | D92: 10.10.135.0 | E92: ="10.10."&A92&".254" -> 10.10.305.254 | F92: /24 | G92: .1-.250 | J92: C262 | M92: =D92&"-254" -> 10.10.135.0-254
A93: 305 | D93: 10.11.49.0 | E93: ="10.11."&#REF!&".254" -> #REF! | F93: /24 | G93: .1-.250
A94: =A93+1 -> 306 | B94: Whatsminer | C94: C268 | D94: 10.10.136.0 | E94: ="10.10."&A94&".254" -> 10.10.306.254 | F94: /24 | G94: .1-.250 | H94: C268 | M94: =D94&"-254" -> 10.10.136.0-254
A95: 306 | D95: 10.11.50.0 | E95: ="10.11."&#REF!&".254" -> #REF! | F95: /24 | G95: .1-.250
A96: =A95+1 -> 307 | B96: Whatsminer | C96: C268 | D96: 10.10.137.0 | E96: ="10.10."&A96&".254" -> 10.10.307.254 | F96: /24 | G96: .1-.250 | I96: C268 | M96: =D96&"-254" -> 10.10.137.0-254
A97: 307 | D97: 10.11.51.0 | E97: ="10.11."&#REF!&".254" -> #REF! | F97: /24 | G97: .1-.250
A98: =A97+1 -> 308 | B98: Whatsminer | C98: C268 | D98: 10.10.138.0 | E98: ="10.10."&A98&".254" -> 10.10.308.254 | F98: /24 | G98: .1-.250 | J98: C268 | M98: =D98&"-254" -> 10.10.138.0-254
A99: 308 | D99: 10.11.52.0 | E99: ="10.11."&#REF!&".254" -> #REF! | F99: /24 | G99: .1-.250
A100: =A99+1 -> 309 | B100: Whatsminer | C100: C253 | D100: 10.10.139.0 | E100: ="10.10."&A100&".254" -> 10.10.309.254 | F100: /24 | G100: .1-.250 | H100: C253 | M100: =D100&"-254" -> 10.10.139.0-254
A101: 309 | D101: 10.11.53.0 | E101: ="10.11."&#REF!&".254" -> #REF! | F101: /24 | G101: .1-.250
A102: =A101+1 -> 310 | B102: Whatsminer | C102: C253 | D102: 10.10.140.0 | E102: ="10.10."&A102&".254" -> 10.10.310.254 | F102: /24 | G102: .1-.250 | I102: C253 | M102: =D102&"-254" -> 10.10.140.0-254
A103: 310 | D103: 10.11.54.0 | E103: ="10.11."&#REF!&".254" -> #REF! | F103: /24 | G103: .1-.250
A104: =A103+1 -> 311 | B104: Antminer | C104: C243 | D104: 10.10.141.0 | E104: ="10.10."&A104&".254" -> 10.10.311.254 | F104: /24 | G104: .1-.250 | H104: C243 | M104: =D104&"-254" -> 10.10.141.0-254
A105: 311 | D105: 10.11.55.0 | E105: ="10.11."&#REF!&".254" -> #REF! | F105: /24 | G105: .1-.250
A106: =A105+1 -> 312 | B106: Antminer | C106: C243 | D106: 10.10.142.0 | E106: ="10.10."&A106&".254" -> 10.10.312.254 | F106: /24 | G106: .1-.250 | I106: C243 | M106: =D106&"-254" -> 10.10.142.0-254
A107: 312 | D107: 10.11.56.0 | E107: ="10.11."&#REF!&".254" -> #REF! | F107: /24 | G107: .1-.250
A108: =A107+1 -> 313 | B108: Whatsminer | C108: C250 / C253 | D108: 10.10.143.0 | E108: ="10.10."&A108&".254" -> 10.10.313.254 | F108: /24 | G108: .1-.250 | I108: C250 | J108: C253 | M108: =D108&"-254" -> 10.10.143.0-254
A109: 313 | D109: 10.11.57.0 | E109: ="10.11."&#REF!&".254" -> #REF! | F109: /24 | G109: .1-.250
A110: =A109+1 -> 314 | B110: Whatsminer | C110: C224 | D110: 10.10.147.0 | E110: ="10.10."&A110&".254" -> 10.10.314.254 | F110: /24 | G110: .1-.250 | H110: C224 | M110: =D110&"-254" -> 10.10.147.0-254
A111: 314 | D111: 10.11.58.0 | E111: ="10.11."&#REF!&".254" -> #REF! | F111: /24 | G111: .1-.250
A112: =A111+1 -> 315 | B112: Antminer | C112: C240 | D112: 10.10.156.0 | E112: ="10.10."&A112&".254" -> 10.10.315.254 | F112: /24 | G112: .1-.250 | H112: C240 | M112: =D112&"-254" -> 10.10.156.0-254
A113: 315 | D113: 10.11.59.0 | E113: ="10.11."&#REF!&".254" -> #REF! | F113: /24 | G113: .1-.250
A114: =A113+1 -> 316 | B114: Antminer | C114: C240 | D114: 10.10.157.0 | E114: ="10.10."&A114&".254" -> 10.10.316.254 | F114: /24 | G114: .1-.250 | I114: C240 | M114: =D114&"-254" -> 10.10.157.0-254
A115: 316 | D115: 10.11.60.0 | E115: ="10.11."&#REF!&".254" -> #REF! | F115: /24 | G115: .1-.250
A116: =A115+1 -> 317 | B116: Antminer | C116: C240 / C249 | D116: 10.10.158.0 | E116: ="10.10."&A116&".254" -> 10.10.317.254 | F116: /24 | G116: .1-.250 | H116: C249 | J116: C240 | M116: =D116&"-254" -> 10.10.158.0-254
A117: 317 | D117: 10.11.61.0 | E117: ="10.11."&#REF!&".254" -> #REF! | F117: /24 | G117: .1-.250
A118: =A117+1 -> 318 | B118: Antminer | C118: C249 | D118: 10.10.159.0 | E118: ="10.10."&A118&".254" -> 10.10.318.254 | F118: /24 | G118: .1-.250 | I118: C249 | M118: =D118&"-254" -> 10.10.159.0-254
A119: 318 | D119: 10.11.62.0 | E119: ="10.11."&#REF!&".254" -> #REF! | F119: /24 | G119: .1-.250
A120: =A119+1 -> 319 | B120: Antminer | C120: C249 | D120: 10.10.160.0 | E120: ="10.10."&A120&".254" -> 10.10.319.254 | F120: /24 | G120: .1-.250 | J120: C249 | M120: =D120&"-254" -> 10.10.160.0-254
A121: 319 | D121: 10.11.63.0 | E121: ="10.11."&#REF!&".254" -> #REF! | F121: /24 | G121: .1-.250
A122: 320 | D122: 10.11.64.0 | E122: ="10.11."&#REF!&".254" -> #REF! | F122: /24 | G122: .1-.250
A123: 321 | D123: 10.11.65.0 | E123: ="10.11."&#REF!&".254" -> #REF! | F123: /24 | G123: .1-.250
A124: 322 | D124: 10.11.66.0 | E124: ="10.11."&#REF!&".254" -> #REF! | F124: /24 | G124: .1-.250
A125: 323 | D125: 10.11.67.0 | E125: ="10.11."&#REF!&".254" -> #REF! | F125: /24 | G125: .1-.250
A126: 324 | D126: 10.11.68.0 | E126: ="10.11."&#REF!&".254" -> #REF! | F126: /24 | G126: .1-.250
A127: 325 | D127: 10.11.69.0 | E127: ="10.11."&#REF!&".254" -> #REF! | F127: /24 | G127: .1-.250
A128: 326 | D128: 10.11.70.0 | E128: ="10.11."&#REF!&".254" -> #REF! | F128: /24 | G128: .1-.250
A129: 327 | D129: 10.11.71.0 | E129: ="10.11."&#REF!&".254" -> #REF! | F129: /24 | G129: .1-.250
A130: 328 | D130: 10.11.72.0 | E130: ="10.11."&#REF!&".254" -> #REF! | F130: /24 | G130: .1-.250
A131: 329 | D131: 10.11.73.0 | E131: ="10.11."&#REF!&".254" -> #REF! | F131: /24 | G131: .1-.250
A132: 330 | D132: 10.11.74.0 | E132: ="10.11."&#REF!&".254" -> #REF! | F132: /24 | G132: .1-.250
...

Sheet Pivot Table 1
A1: COUNTA of Container
A2: 287
C3: 43 | E3: 3 Days | F3: CB - Open Disconnect
C6: 47 | E6: 3 Days | F6: CB - Open Disconnect
C9: 6 | E9: 1 Day | F9: Constellation Switchgear
C11: 17 | E11: 1 Day | F11: CB
C14: 15 | E14: 1 Day | F14: CB
C17: 16 | E17: 1 Day | F17: CB
C20: 17 | E20: 1 Day | F20: CB
C23: 2

Sheet Outage Plan
B1: MDC # | C1: Customer | D1: Substation Breaker Name (CN) | E1: Anticipated Outage Date
B2: C009 | C2: US Bitcoin Corp | D2: 11A | E2: 45092
B3: C010 | C3: US Bitcoin Corp | D3: 11A | E3: 45092
B4: C011 | C4: US Bitcoin Corp | D4: 11A | E4: 45092
B5: C012 | C5: US Bitcoin Corp | D5: 11A | E5: 45092
B6: C013 | C6: US Bitcoin Corp | D6: 11A | E6: 45092
B7: C014 | C7: US Bitcoin Corp | D7: 11A | E7: 45092
B8: C015 | D8: 11A | E8: 45092
B9: C016 | C9: US Bitcoin Corp | D9: 11A | E9: 45092
B10: C017 | D10: 11A | E10: 45092
B11: C018 | D11: 11A | E11: 45092
B12: C019 | C12: Compass Mining | D12: 11A | E12: 45092
B13: C020 | C13: Marathon Patent Group, Inc | D13: 11A | E13: 45092
B14: C132 | C14: US Bitcoin Corp | D14: 11B | E14: 45092
B15: C144 | C15: US Bitcoin Corp | D15: 11B | E15: 45092
B16: C145 | C16: US Bitcoin Corp | D16: 11B | E16: 45092
B17: C146 | C17: US Bitcoin Corp | D17: 11B | E17: 45092
B18: C147 | C18: US Bitcoin Corp | D18: 11B | E18: 45092
B19: C148 | C19: US Bitcoin Corp | D19: 11B | E19: 45092
B20: C149 | C20: US Bitcoin Corp | D20: 11B | E20: 45092
B21: C156 | C21: Sphere 3D | D21: 11B | E21: 45092
B22: C157 | D22: 11B | E22: 45092
B23: C158 | D23: 11B | E23: 45092
B24: C159 | C24: Integrated Ventures | D24: 11B | E24: 45092
B25: C160 | D25: 11B | E25: 45092
B26: C161 | D26: 11B | E26: 45092
B27: C162 | D27: 11B | E27: 45092
B28: C163 | D28: 11B | E28: 45092
B29: C120 | C29: Touzi Capital | D29: 11C | E29: 45092
B30: C133 | C30: US Bitcoin Corp | D30: 11C | E30: 45092
B31: C134 | C31: US Bitcoin Corp | D31: 11C | E31: 45092
B32: C135 | C32: US Bitcoin Corp | D32: 11C | E32: 45092
B33: C136 | C33: US Bitcoin Corp | D33: 11C | E33: 45092
B34: C137 | D34: 11C | E34: 45092
B35: C138 | C35: Compass Mining | D35: 11C | E35: 45092
B36: C139 | C36: Compass Mining | D36: 11C | E36: 45092
B37: C140 | D37: 11C | E37: 45092
B38: C141 | D38: 11C | E38: 45092
B39: C150 | C39: Compass Mining | D39: 11C | E39: 45092
B40: C151 | C40: Compass Mining | D40: 11C | E40: 45092
B41: C152 | C41: Compass Mining | D41: 11C | E41: 45092
B42: C153 | D42: 11C | E42: 45092
B43: C154 | D43: 11C | E43: 45092
B44: C155 | D44: 11C | E44: 45092
B45: C085 | D45: 12A | E45: 45091
B46: C097 | C46: Touzi Capital | D46: 12A | E46: 45091
B47: C109 | C47: Touzi Capital | D47: 12A | E47: 45091
B48: C121 | C48: Touzi Capital | D48: 12A | E48: 45091
B49: C122 | C49: Compass Mining | D49: 12A | E49: 45091
B50: C123 | C50: Compass Mining | D50: 12A | E50: 45091
B51: C124 | C51: Compass Mining | D51: 12A | E51: 45091
B52: C125 | C52: Compass Mining | D52: 12A | E52: 45091
B53: C126 | C53: Compass Mining | D53: 12A | E53: 45091
B54: C127 | D54: 12A | E54: 45091
B55: C128 | D55: 12A | E55: 45091
B56: C129 | C56: Compass Mining | D56: 12A | E56: 45091
B57: C130 | D57: 12A | E57: 45091
B58: C131 | D58: 12A | E58: 45091
B59: C142 | D59: 12A | E59: 45091
B60: C143 | D60: 12A | E60: 45091
B61: C063 | C61: Marathon Patent Group, Inc | D61: 12B | E61: 45090
B62: C074 | C62: Marathon Patent Group, Inc | D62: 12B | E62: 45090
B63: C086 | C63: Marathon Patent Group, Inc | D63: 12B | E63: 45090
B64: C098 | C64: Touzi Capital | D64: 12B | E64: 45090
B65: C099 | C65: Touzi Capital | D65: 12B | E65: 45090
B66: C100 | C66: Touzi Capital | D66: 12B | E66: 45090
B67: C110 | C67: Touzi Capital | D67: 12B | E67: 45090
B68: C111 | C68: Us Bitcoin Corp | D68: 12B | E68: 45090
B69: C112 | C69: Us Bitcoin Corp | D69: 12B | E69: 45090
B70: C113 | D70: 12B | E70: 45090
B71: C114 | C71: Sphere 3D | D71: 12B | E71: 45090
B72: C115 | C72: Sphere 3D | D72: 12B | E72: 45090
B73: C116 | C73: US Bitcoin Corp | D73: 12B | E73: 45090
B74: C117 | C74: Sphere 3D | D74: 12B | E74: 45090
B75: C118 | C75: Sphere 3D | D75: 12B | E75: 45090
B76: C119 | C76: Touzi Capital | D76: 12B | E76: 45090
B77: C087 | C77: Compass Mining | D77: 12C | E77: 45089
B78: C088 | C78: Compass Mining | D78: 12C | E78: 45089
B79: C089 | C79: Compass Mining | D79: 12C | E79: 45089
B80: C090 | C80: Decimal / Integrated Ventures | D80: 12C | E80: 45089
B81: C091 | C81: Compass Mining | D81: 12C | E81: 45089
B82: C092 | C82: Compass Mining | D82: 12C | E82: 45089
B83: C093 | C83: Compass Mining | D83: 12C | E83: 45089
B84: C094 | D84: 12C | E84: 45089
B85: C101 | C85: Compass Mining | D85: 12C | E85: 45089
B86: C102 | C86: Marathon Patent Group, Inc | D86: 12C | E86: 45089
B87: C103 | C87: Marathon Patent Group, Inc | D87: 12C | E87: 45089
B88: C104 | C88: Marathon Patent Group, Inc | D88: 12C | E88: 45089
B89: C105 | C89: Compass Mining | D89: 12C | E89: 45089
B90: C106 | C90: Marathon Patent Group, Inc | D90: 12C | E90: 45089
B91: C107 | C91: Marathon Patent Group, Inc | D91: 12C | E91: 45089
B92: C075 | C92: Compass Mining | D92: 21A | E92: 45083
B93: C076 | C93: Compass Mining | D93: 21A | E93: 45083
B94: C077 | C94: US Bitcoin Corp | D94: 21A | E94: 45083
B95: C078 | C95: US Bitcoin Corp | D95: 21A | E95: 45083
B96: C079 | C96: US Bitcoin Corp | D96: 21A | E96: 45083
... B154: C084 | C154: Touzi Capital | D154: 24C | E154: 45086
B155: C096 | D155: 24C | E155: 45086
B156: C108 | C156: Touzi Capital | D156: 24C | E156: 45452
B157: C001 | C157: Marathon Patent Group, Inc | D157: 1A | E157: 45097
...

Sheet VLAN issues
B2: Container | C2: Issue
B3: C063 | C3: VLAN > 255
B4: C074 | C4: VLAN > 255
B5: C085 | C5: VLAN > 255
B6: C086 | C6: VLAN > 255
B7: C097 | C7: VLAN > 255
B8: C100 | C8: VLAN > 255
B9: C103 | C9: VLAN > 255
B10: C104 | C10: VLAN > 255
B11: C106 | C11: VLAN > 255
B12: C107 | C12: VLAN > 255
B13: C109 | C13: VLAN > 255
... B20: C119 | C20: VLAN > 255

Sheet Miner Types
A1: Model | B1: Ideal Hashrate (TH) | C1: Sticker Efficiency (W/TH) | D1: Power Consumption (W) | E1: Model | F1: Antminer S19 (86T) | G1: Antminer S19 (90T) | H1: Antminer S19 (95T) | I1: Antminer S19 Pro (105T) | J1: Antminer S19 Pro (110T) | K1: Antminer S19j Pro (100T) | L1: Antminer S19j Pro (104T) | M1: Antminer S19j Pro (88T) | N1: Antminer S19j Pro (92T) | O1: Antminer S19j Pro (96T) | P1: Antminer S19XP (134T) | Q1: Antminer S19XP (141T) | R1: Whatsminer M30S (82T) | S1: Whatsminer M30S (84T) | T1: Whatsminer M30S (86T) | U1: Whatsminer M30S (88T) | V1: Whatsminer M30S (90T) | W1: Whatsminer M30S (92T) | X1: Whatsminer M30S (94T) | Y1: Whatsminer M30S+ (100T) | Z1: Whatsminer M30S+ (102T) | AA1: Whatsminer M30S+ (104T) | AB1: Whatsminer M30S+ (96T) | AC1: Whatsminer M30S+ (98T) | AD1: Whatsminer M30S++ (104T) | AE1: Whatsminer M30S++ (106T) | AF1: Whatsminer M30S++ (108T) | AG1: Whatsminer M30S++ (110T) | AH1: Whatsminer M31S (74T)
A2: Antminer S19 (86T) | B2: 86 | C2: 34 | D2: =B2*C2 -> 2924 | E2: Ideal Hashrate (TH) | F2: 86 | G2: 90 | H2: 95 | I2: 105 | J2: 110 | K2: 100 | L2: 104 | M2: 88 | N2: 92 | O2: 96 | P2: 134 | Q2: 141 | R2: 82 | S2: 84 | T2: 86 | U2: 86 | V2: 90 | W2: 92 | X2: 94 | Y2: 100 | Z2: 102 | AA2: 104 | AB2: 96 | AC2: 98 | AD2: 104 | AE2: 106 | AF2: 108 | AG2: 110 | AH2: 74
A3: Antminer S19 (90T) | B3: 90 | C3: 34 | D3: =B3*C3 -> 3060 | E3: Sticker Efficiency (W/TH) | F3: 34 | G3: 34 | H3: 34 | I3: 29.5 | J3: 29.5 | K3: 29.5 | L3: 29.5 | M3: 29.5 | N3: 29.5 | O3: 29.5 | P3: 21.5 | Q3: 21.5 | R3: 38 | S3: 38 | T3: 38 | U3: 38 | V3: 38 | W3: 38 | X3: 38 | Y3: 34 | Z3: 34 | AA3: 34 | AB3: 34 | AC3: 34 | AD3: 31 | AE3: 31 | AF3: 31 | AG3: 31 | AH3: 44
A4: Antminer S19 (95T) | B4: 95 | C4: 34 | D4: =B4*C4 -> 3230 | E4: Power Consumption (W) | F4: =F2*F3 -> 2924 | G4: =G2*G3 -> 3060 | H4: =H2*H3 -> 3230 | I4: =I2*I3 -> 3097.5 | J4: =J2*J3 -> 3245 | K4: =K2*K3 -> 2950 | L4: =L2*L3 -> 3068 | M4: =M2*M3 -> 2596 | ... AH4: =AH2*AH3 -> 3256
A5: Antminer S19 Pro (105T) | B5: 105 | C5: 29.5 | D5: =B5*C5 -> 3097.5
A6: Antminer S19 Pro (110T) | B6: 110 | C6: 29.5 | D6: =B6*C6 -> 3245
A7: Antminer S19j Pro (100T) | B7: 100 | C7: 29.5 | D7: =B7*C7 -> 2950
A8: Antminer S19j Pro (104T) | B8: 104 | C8: 29.5 | D8: =B8*C8 -> 3068
A9: Antminer S19j Pro (88T) | B9: 88 | C9: 29.5 | D9: =B9*C9 -> 2596
A10: Antminer S19j Pro (92T) | B10: 92 | C10: 29.5 | D10: =B10*C10 -> 2714
A11: Antminer S19j Pro (96T) | B11: 96 | C11: 29.5 | D11: =B11*C11 -> 2832
A12: Antminer S19XP (134T) | B12: 134 | C12: 21.5 | D12: =B12*C12 -> 2881
A13: Antminer S19XP (141T) | B13: 141 | C13: 21.5 | D13: =B13*C13 -> 3031.5
A14: Whatsminer M30S (82T) | B14: 82 | C14: 38 | D14: =B14*C14 -> 3116
A15: Whatsminer M30S (84T) | B15: 84 | C15: 38 | D15: =B15*C15 -> 3192
A16: Whatsminer M30S (86T) | B16: 86 | C16: 38 | D16: =B16*C16 -> 3268
... A30: Whatsminer M31S (74T) | B30: 74 | C30: 44 | D30: =B30*C30 -> 3256

Sheet Labor
A1: Date | B1: 44575 | C1: 44582 | D1: 44589 | E1: 44596 | F1: 44603 | G1: 44610 | H1: 44617 | I1: 44624 | J1: 44631 | K1: 44638 | L1: 44645 | M1: 44652
A3: Energize | I3: =7*560 -> 3920 | K3: =7*560 -> 3920 | M3: =7*560 -> 3920
A4: Total Energized | I4: =I3+H4 -> 3920 | J4: =J3+I4 -> 3920 | K4: =K3+J4 -> 7840 | L4: =L3+K4 -> 7840 | M4: =M3+L4 -> 11760
A6: Delivery | F6: 6500 | G6: 3500 | L6: 1760
A7: Total Delivered | B7: =B6 -> 0 | F7: =E7+F6 -> 6500 | G7: =F7+G6 -> 10000 | H7: =G7+H6 -> 10000 | I7: =H7+I6 -> 10000 | J7: =I7+J6 -> 10000 | K7: =J7+K6 -> 10000 | L7: =K7+L6 -> 11760 | M7: =L7+M6 -> 11760
A14: Labor | B14: Hours | C14: Minutes
A15: Unboxing | B15: =C15/60 -> 0.05 | C15: 3
A16: Loading | B16: =C16/60 -> 0.083333333 | C16: 5
A19: Days/ Week | B19: 5
A20: Hours/ Day | B20: 7
A21: Hours/ Week | B21: =B19*B20 -> 35
B23: Week/ Worker | C23: Day/ Worker
A24: Unboxed | B24: =B21/B15 -> 700 | C24: =B20/B15 -> 140
A25: Loaded | B25: =B21/B16 -> 420 | C25: =B20/B16 -> 84
A27: Employee Max | B27: 10

Sheet Land Clearing
B1: Firm | C1: Acres | D1: Total Cost | E1: Price per Acre
B2: Pierce Land Clearing | C2: 10 | D2: 40000 | E2: =D2/C2 -> 4000
B3: Lozoya | C3: 12 | D3: 30472 | E3: =D3/C3 -> 2539.3333
B4: Williams Paving | C4: 10 | D4: 2,500 - 3,000 | E4: 2700

Sheet Geotech Survey
B1: Firm | C1: Phase 1 Cost | D1: Phase 2 | E1: Land Clearing Cost | F1: Total Cost
B2: Beyond | C2: 12000 | D2: 20000 | E2: TBD | F2: =SUM(C2:E2) -> 32000
B3: Terracon | C3: 13800 | D3: 18700 | E3: TBD | F3: 32500

Sheet Container Ratio
C1: Miners/Unit | D1: MW/Unit | E1: MW/Unit (M30s) | F1: $/Unit | G1: $/MW | H1: $/MW (M30s) | K1: Site
B2: Tessarack | C2: 968 | D2: 3.45 | E2: =C2*K4/1000000 -> 3.2912 | F2: 613000 | G2: =F2/D2 -> 177681.16 | H2: =F2/E2 -> 186254.25 | J2: Megawatts | K2: 42
B3: RK | C3: 560 | D3: 2 | E3: =C3*K4/1000000 -> 1.904 | F3: 315000 | G3: =F3/D3 -> 157500 | H3: =F3/E3 -> 165441.18 | K3: M30s
J4: Watts | K4: 3400
G6: MW Limit
A7: Option 1 | C7: Units | D7: Total Spots | E7: Total MW (M30s) | G7: Container | H7: Site | J7: Total $ | K7: $/Miner
B8: Tessarack | C8: 0 | D8: =C8*$C$2 -> 0 | E8: =$E$2*C8 -> 0 | G8: =C8*$D$2 -> 0 | H8: =E8 -> 0 | J8: =C8*$F$2 -> 0 | K8: =J8/D14 -> #DIV/0!
B9: RK | C9: 21 | D9: =C9*$C$3 -> 11760 | E9: =$E$3*C9 -> 39.984 | G9: =C9*$D$3 -> 42 | H9: =K2-E8 -> 42 | J9: =C9*$F$3 -> 6615000 | K9: =J9/D15 -> 562.5
B10: Total | C10: =C9+C8 -> 21 | D10: =D9+D8 -> 11760 | E10: =SUM(E8:E9) -> 39.984 | G10: =G9+G8 -> 42 | H10: =H9+H8 -> 42 | J10: =J9+J8 -> 6615000 | K10: =J10/D16 -> 562.5
G12: Underutilization
C13: MW Utilization | D13: Active Miners | G13: Container | H13: Site
B14: Tessarack | C14: =MIN(E8,G8,H8) -> 0 | D14: =C14*1000000/$K$4 -> 0 | G14: =D8-D14 -> 0
B15: RK | C15: =MIN(E9,G9,H9) -> 39.984 | D15: =C15*1000000/$K$4 -> 11760 | G15: =D9-D15 -> 0
B16: Total | C16: =MIN(E10,G10,H10) -> 39.984 | D16: =D14+D15 -> 11760 | G16: =D10-D16 -> 0 | H16: =K2*1000000/K4-D16 -> 592.94118
G18: MW Limit
A19: Option 2 | C19: Units | D19: Total Spots | E19: Total MW (M30s) | G19: Container | H19: Site | J19: Total $ | K19: $/Miner
B20: Tessarack | C20: 0 | D20: =C20*$C$2 -> 0 | E20: =$E$2*C20 -> 0 | G20: =C20*$D$2 -> 0 | H20: =E20 -> 0 | J20: =C20*$F$2 -> 0 | K20: =J20/D26 -> #DIV/0!
B21: RK | C21: 22 | D21: =C21*$C$3 -> 12320 | E21: =$E$3*C21 -> 41.888 | G21: =C21*$D$3 -> 44 | H21: =K2-E20 -> 42 | J21: =C21*$F$3 -> 6930000 | K21: =J21/D27 -> 562.5
B22: Total | C22: =C21+C20 -> 22 | D22: =D21+D20 -> 12320 | E22: =SUM(E20:E21) -> 41.888 | G22: =G21+G20 -> 44 | H22: =H21+H20 -> 42 | J22: =J21+J20 -> 6930000 | K22: =J22/D28 -> 562.5
G24: Underutilization
C25: MW Utilization | D25: Active Miners | G25: Container | H25: Site
B26: Tessarack | C26: =MIN(E20,G20,H20) -> 0 | D26: =C26*1000000/$K$4 -> 0 | G26: =D20-D26 -> 0
B27: RK | C27: =MIN(E21,G21,H21) -> 41.888 | D27: =C27*1000000/$K$4 -> 12320 | G27: =D21-D27 -> 0
B28: Total | C28: =MIN(E22,G22,H22) -> 41.888 | D28: =MIN(D26+D27,K2*1000000/K4) -> 12320 | G28: =D22-D28 -> 0 | H28: =K2*1000000/K4-D28 -> 32.941176
H30: $ | I30: Miners | J30: $/Miner | K30: $/Additional
B31: Assumptions: | G31: Option 1 | H31: =J10 -> 6615000 | I31: =D16 -> 11760 | J31: =K10 -> 562.5
B32: 1. Leaving an RK vacant is preferred to leaving a Tessarack vacant | G32: Option 2 | H32: =J22 -> 6930000 | I32: =D28 -> 12320 | J32: =K22 -> 562.5
B33: 2. Only cost is that of the containers. Cost of transformer could be added to $/Unit | G33: Difference | H33: =H31-H32 -> -315000 | I33: =I31-I32 -> -560 | J33: =J31-J32 -> 0 | K33: =H33/I33 -> 562.5

Sheet Sound Concern
B2: Container | C2: Risk Level
B3: C163 | C3: High
B4: C153 | C4: High
B5: C141 | C5: High
B6: C155 | C6: High
B7: C143 | C7: High
B8: C130 | C8: High
B9: C118 | C9: High
B10: C131 | C10: High
B11: C119 | C11: High
B12: C106 | C12: High
B13: C094 | C13: High
... B44: C034 | C44: Medium
